{"carbaminohemoglobin":"[医] 氨基甲酰血红蛋白","carbamite":"卡巴买特, 二乙二苯基脲(一种固体火箭燃烧组分)","carbamonitrile":"[化] 氨基化氰; 腈氨","carbamoyl":"n. [化]氨基甲酰","carbamoylation":"甲氨酰化(作用)","carbamoylglyoxaline":"[化] 氨基甲酰甘喔啉","Carbamult":"勐杀威","carbamyl":"n. [化]氨基甲酰","carbamyltaurine":"[化] 氨甲酰牛磺酸","carbamyltransferase":"[化] 氨甲酰基转移酶; 转氨甲酰酶","carbamylurea":"[机] 缩二","carbanalyzer":"定碳仪","carbanil":"异氰酸苯酯","carbanilide":"[化] N-碳酰苯胺; 对称二苯脲","carbanilino":"(=carbaniloyl, phenylcarbamoyl) 苯氨基甲酰","carbaniloyl":"[建] 苯氨基甲酰","carbanion":"n. 负碳离子","carbanite":"卡巴耐特炸药","carbap":"abbr. Confederacion de Asociaciones Rurales de Buenos Aires y la Pampa （西班牙语）<阿根廷>布谊诺斯艾利斯和拉潘帕农民协会联合会","carbapatite":"碳酸磷灰石","carbarn":"n. 车库","carbarsone":"卡巴胂, 对脲苯基胂酸","carbaryl":"n. [化]西维因, 胺甲萘(接触性杀毒剂)","carbasar":"玻璃纤维增强聚碳酸酯","carbaso":"绢丝薄绸","carbassus":"西班牙亚麻布","carbasus":"[医] 纱布","Carbatene":"代森联","carbazide":"(=carbohydrazide)卡巴肼, 卡巴脲, 二肼羰, 均二氨基脲","carbazochrom":"[化] 卡巴克络","carbazochrome":"[化] 卡巴克洛","carbazolamine":"咔唑胺","carbazole":"n. [化]咔唑","carbazolyl":"[化] 咔唑基; 氮芴基","carbazone":"[药]卡巴胂, 缩(对称)二氨基脲","carbazone,diphenyl":"[化] 二苯卡巴腙","carbazotate":"[医] 苦味酸盐","carbazyl":"卡唑基","carbecue":"n. 热压熔化废旧汽车的装置,熔车装置","carbenarsone":"[医] 卡巴胂, 对脲基苯胂酸","carbendazim":"[化] 多菌灵","carbendazol":"[化] 多菌灵","carbene":"n. [化]卡宾,碳烯","carbenes":"[建] 碳质沥青","carbenez":"[化] 聚炔","carbenicillin":"n. [微]羧苄青霉素","carbenium":"(=carbonium)碳(离子), 碳正离子","carbenoid":"[化] 卡宾体","carbenoxalone":"氢琥珀酸甘草次酸","carbenoxolone":"n. [药]生胃酮(用于治疗胃溃疡)","carbenzol":"岩焦油酚","Carberry":"卡伯里","carbetamide":"长杀草","carbetapentane":"[化] 喷托维林; 咳必清","carbethoxy":"(=ethoxycarbonyl)乙酸基, 乙氧甲酰","carbethoxyl":"[建] 乙酯基","carbethoxylation":"[化] 乙酯基化作用; 引入乙酯基","carbetidine":"[化] 醇苯哌酯","carbex":"炭黑胶乳","carbhemogiobin":"[建] 碳酸血红朊","carbhemoglobin":"[化]碳酸血红朊","Carbicron":"百治磷","carbide":"n. 碳化物\\n[化] 碳化物; 碳化钙; 电石","carbides":"(carbide 的复数) n. 碳化物\\n[化] 碳化物; 碳化钙; 电石","carbidopa":"[化] 卡比多巴; 甲基多巴肼","carbimazol":"[化] 甲亢平","carbimazole":"[化] 甲亢平","carbimide":"碳酰亚胺, 异氰酸脂","carbimides":"[医] 羰基胺类","carbin":"[人名] 卡宾","carbine":"n. 卡宾枪","carbineer":"n. 卡宾枪手","carbines":"n. （原为骑兵用的）卡宾枪, 轻型半自动或自动步枪( carbine的复数形式 )","carbinol":"n. 甲醇\\n[化] 甲醇","carbinoxamine":"[化] 卡比沙明; 吡氯苄氧胺","carbinyl":"甲基","carbiphene":"[化] 卡比芬","carbite":"金刚石","carbitol":"卡必醇","carbium":"卡毕阿姆铝铜合金","carbo":"n. <美口>碳水化合物食品,含糖食品","carbo-":"pref. 碳(酸), 羰\\n[建] 碳, 羰","carbo-alcohol":"[医] 石炭酸酒精","carbo-corundum":"[建] 碳钢玉","carboamidation":"[化] 氨羰基化","carboanion":"[化] 碳阴离子","carbobenzoxy":"[建] 苯酯基","carbobenzoxy-(Cbz)":"[化] 苄酯基; 苄氧羰基","carbobenzoxyglycine":"[医] 苄氧羰甘氨酸","carbobenzoyl":"[化] 羧苯甲酰; 某羰苯甲酸","carbobenzyloxychloride":"[化] 苄酯基氯; 苯甲氧甲酰氯; 氯甲酸苄酯; 苄氧羰基氯","carboborite":"水碳硼钙镁石; 水碳硼石","carbocaine":"[医] 卡抱卡因(麻醉药)","carbocation":"碳阳离子","carbocations":"(carbocation 的复数) 碳阳离子","carbocer":"稀土沥青","carbocerine":"镧石","carbochain":"碳链","carbocholine":"碳胆碱","carbochromen":"乙胺香豆素","carbocloral":"[化] 卡波氯醛; 氯醛尿烷","carbocoal":"半焦","carbocromene":"乙胺香豆素","carbocyanine":"羰花青","carbocycle":"[建] 碳环","carbocyclic":"a. 碳环形的","carbocysteine":"[化] 羧甲半胱氨酸","carbodi-imide":"[化] 碳(化)二亚胺(HN:C:NH)","carbodiazide":"二肼羰, 卡巴氮","carbodiazone":"[化] (某)双偶氮酮(指含有二价基-N:N·CON:N-的化合物)","carbodihydrazide":"[机] 卡二酰","carbodiimide":"[化] 碳二亚胺\\n[医] 碳化二亚胺","carbodiphenylimide":"[化] 碳化双苯亚胺(C-6H-5N:C:NC-6H-5)","carbodynamite":"含碳硝化甘油","carboform":"碳纤维","carbofos":"[化] 马拉硫磷","carbofrax":"[建] 金刚硅砖料","carbofuran":"[化] 呋喃丹; 卡巴呋喃; 克百威","carbogaseous":"[医] 含二氧化碳气的","carbogel":"煤胶体","carbogen":"[医] 卡波金(含5%二氧化碳的氧)","carbogenes":"[建] 碳合气","carbohemia":"碳酸血症, 二氧化碳血症","carbohemoglobin":"(=carbhemoglobin)[生化]碳酸血红蛋白","carbohm":"电阻测碳仪","carbohumin":"[地质]碳胡敏素","carbohydrase":"n. [生化]糖酶","carbohydrate":"n. 碳水化合物, 糖类\\n[化] 糖类; 碳水化合物","carbohydrates":"n. 碳水化合物, 糖类( carbohydrate的复数形式 ); 淀粉质或糖类食物","carbohydraturia":"[医] 糖类尿, 糖尿","carbohydrazide":"碳酰肼, 卡巴肼, 均二氨基脲","carbohydrogenic":"[医] 生糖的","carboid":"油焦质","carboids":"炭青质","carbol-thionine":"[医] 石炭酸硫紫","carbolate":"[化]酚盐, 石炭酸盐","carbolated":"a. 浸以石炭酸的","carbolfuchsin":"酚品红液, 卡宝品红","carbolic":"a. 碳制的, 用煤焦油制成的\\n[医] 石炭酸的","carboligase":"聚醛酶","carboline":"n. [化]咔啉","carbolineum":"n. 蒽油；焦油木材防腐剂","carbolism":"石炭酸中毒, 酚中毒","carbolismus":"石碳酸中毒","carbolite":"[电] 电木","carbolize":"vt. 以石炭酸处理\\n[医] 加石炭酸, 石炭酸处理","carbolloy":"[机] 锻接碳化物","carbollysoform":"[医] 酚来苏仿(成药,含酚3%的来苏仿)","carbolon":"[建] 卡包纶","carboloy":"钨钴硬质合金(用钴作粘结剂的碳化钨硬质合金)","carboluria":"[医] 石炭酸尿, 酚尿","carbolxylene":"[医] 石炭酸二甲苯混合液(制显微镜切片用)","carbometer":"(测定空气中的)氧化碳计, 空气碳酸计","carbomethoxy":"[化] 甲酯基; 甲氧甲酰","carbometoxyl":"甲氧碳基","carbometry":"[医] 碳酸定量法, 二氧化碳定量法","carbomite":"碳酰胺","carbomycin":"n. [微]碳霉素","carbon":"n. 碳, 副本, 复写纸\\n[化] 碳","carbon-14":"[化] 碳14","carbon-bearing":"带碳，含碳的","carbon-coated":"[化] 被炭沉积覆盖的","carbon-containing":"含碳的","carbon-copied":"vt. carbon-copy的变形","carbon-date":"碳定年代\\n碳素测定年代","carbon-dated":"(carbon-date 的过去分词) 碳定年代\\n碳素测定年代","carbon-free":"[建] 不含碳的","carbon-neutral":"碳中和","carbon-nitrogen-oxygen":"[医]碳-氮-氧","carbon-producing":"[建] 生碳的","carbon-white":"[化] 白炭黑(为SiO-2,白色补强剂)","carbona":"不规则锡矿床","carbonaceous":"a. 碳的, 碳质的, 含碳的\\n[建] 含碳的","carbonade":"n. (洋葱啤酒)烩牛肉","carbonado":"n. 烤肉, 烤鱼\\nvt. 烤","carbonadoed":"v. 黑金刚石( carbonado的过去式和过去分词 )","carbonadoes":"vt. 烧；烤\\nn. [矿物] 黑金刚石；烤鱼, 烤肉","carbonadoing":"v. 黑金刚石( carbonado的现在分词 )","carbonados":"n. 黑金刚石( carbonado的名词复数 )","carbonara":"<意>n.烤面条加干酪沙司","Carbonari":"<意>[复]n.烧炭党(19世纪意大利的革命组织,旨在统一意大利,建立共和国) , 烧炭党人","carbonarism":"n. （意）烧炭党（十九世纪意大利的革命组织）；烧炭党人 (Carbonari的变形)","carbonas":"[医] 碳酸盐","carbonatation":"n. [化]二氧化碳饱和","carbonate":"n. 碳酸盐\\nvt. 使碳酸盐化, 使充满二氧化碳","carbonated":"a. 含二氧化碳的；碳化的, 碳酸的","carbonates":"n. 碳酸盐( carbonate的名词复数 )\\nv. 充二氧化碳于( carbonate的第三人称单数 )","carbonating":"[建] 碳酸化, 充碳酸气","carbonation":"n. 二氧化碳饱和, 碳化作用\\n[化] 碳酸化; 碳化","carbonatite":"n. [地]碳酸盐岩","carbonatization":"[建] 碳酸饱充作用","carbonato":"含碳酸盐的","carbonator":"[化] 碳酸化器\\n[医] 碳酸化器","carbondale":"[地名] [加拿大、美国] 卡本代尔","carbone":"[医] 痈","carbonell":"[人名] [英格兰人姓氏] 卡博内尔绰号，头发或肤色黑者，来源于盎格鲁诺曼底法语，含义是“木炭”(charcoal)","carbonemia":"碳酸血症, 一氧化碳血症","carboneol":"[医] 卡邦尼奥(煤焦油溶于四氯化碳中所得的黑色液体,治皮肤病)","carboneum":"[医] 碳(6号元素)","carboni":"[人名] 卡尔博尼","carbonic":"a. 碳的, 由碳得到的\\n[医] 碳的","carbonicacid":"gas[化]碳酸气,二氧化碳","carbonide":"碳化物(指金属碳化物)","Carboniferous":"n. 石炭纪, 石炭层\\na. 含碳或煤的","carbonification":"[化] 碳化作用","carbonify":"[建] 碳化","carbonifying":"[建] 碳化的","carboniogenesis":"正碳离子源","carbonisation":"碳化","carbonise":"v. <主英>=carbonize","carbonite":"n. 硝酸甘油, 硝酸钾\\n[化] 碳质炸药(硝化甘油、硝酸钾、锯屑炸药)","carbonitride":"碳氮化物","carbonitriding":"碳氮共渗, 氰化(合物)","carbonitrile":"[化]腈","carbonium":"[建] 阳碳","carbonization":"n. 碳化(作用)\\n[化] 碳化; 碳化作用; 碳酸化; 炭化","carbonize":"vt. 使焦化, 使碳化, 使与碳化合\\n[医] 碳化","carbonized":"v. 碳化","carbonizer":"[化] (氯化铝)去纤维素液; 碳化塔","carbonizes":"vt. 使成碳, 碳化, 使与碳化合（carbonize的第三人称单数形式）","carbonizing":"[化] 碳化的; 碳化","carbonless":"a. 无碳的","carbonnade":"n. (洋葱啤酒)炖牛肉","carbonoid":"[化] 类碳型; 碳构型","carbonolite":"碳质岩","carbonometer":"[医] 碳酸定量器, 二氧化碳定量器","carbonometry":"[医] 碳酸定量法, 二氧化碳定量法","carbonous":"[建] 碳的, 含碳的","carbons":"n. <化>碳( carbon的复数形式 ); 复写纸","carbonuria":"[医] 碳酸尿[症]","carbonyl":"[医] 羰基, 碳酰","carbonyl-monothio-acid":"[化] 一硫羟碳酸","carbonylamines":"[医] 羰基胺类","carbonylate":"[建] 引入羰基","carbonylation":"[化] 羰基化; 羰基化作用","carbonyldioxy":"[化] 碳酰二氧基; 碳酸基","carbonylhemoglobin":"[机] 一氧化碳血红素","carbonylic":"a. [化]碳酰基的, 羰基的","carbonyls":"(carbonyl 的复数) [医] 羰基, 碳酰","carbophenothion":"[机] 二硫磷","carbophile":"亲碳性","carbophilic":"[医] 嗜碳酸气的","carboplatin":"n. 卡波铂","carbopol":"聚羧乙烯; 聚羧乙烯","carboprost":"[化] 卡前列素","carboquone":"[化] 卡波醌","carboraffin":"糖用活性炭","carborane":"n. [化]碳硼烷","carboranes":"(carborane 的复数) n.[化]碳硼烷","carborne":"汽车转运","Carboround":"碳化硅载体","carborundum":"n. 碳化硅, 金刚砂\\n[化] 金刚砂; 碳化硅","carbosand":"碳化砂","carbosant":"[化] 碳酸檀香酯","carbosapol":"[医] 碳酸肥皂","carbostibamide":"[医] 脲╃胺","carbostyri1":"[医] 羟基喹啉","carbostyril":"[化] 喹诺酮; 2-羟基喹啉","carbothermal":"(=carbothermic) 用碳高温还原的, 碳热还原的","carbothialdine":"[化] 二硫代氨基甲酸二乙胺盐","Carbowax":"聚乙二醇(商品名), 水溶性有机润滑剂","carbox-":"羧基","carboxide":"n. 羰基\\n[化] 环氧乙烷二氧化碳1:9混合物商品名","carboxin":"[化] 萎锈灵","carboxy":"n. [有化] 羧基","carboxy-":"[医]羧基","carboxy-peptidase":"[医] 羧肽酶","carboxyamidase":"羧基酰胺酶","carboxyarsenazo":"偶氮胂羧","carboxybiotin":"羧基生物素","Carboxydomonas":"[医] 碳氧单胞菌属","carboxyethyl":"[化] 羧乙基","carboxyhaemoglobin":"[化] 碳氧血红蛋白","carboxyhemoglobin":"羧络[碳氧]血红蛋白","carboxyhemoglobinemia":"[医] 碳氧血红蛋白血症, 一氧化碳中毒","carboxyl":"n. 羧(基)\\n[化] 羧基","carboxylamine":"[化] 氨甲酸; 氨基甲酸","carboxylase":"n. [化]碳酸酵素","carboxylate":"n. 羰化物\\n[化] 羧化物; 羧酸盐(或酯)","carboxylated":"n. [有化] 羧酸盐；羧化物","carboxylates":"羧化物; 羧化物","carboxylation":"[化] 羧基化; 羧化; 羧化作用\\n[医] 羧化[作用]","carboxylesterase":"羧酸酯酶","carboxylic":"[机] 羧基的","carboxylol":"[医] 石炭酸二甲苯","carboxyls":"(carboxyl 的复数) n. 羧(基)\\n[化] 羧基","carboxyltransferase":"羧基转移酶","carboxymethocel":"[医] 羧甲基纤维素","carboxymethyl":"[建] 羧甲基","carboxymethylcellulose":"[医] 羧甲基纤维素","carboxypeptidase":"n. [生化]羧肽酶","carboxypeptidases":"(carboxypeptidase 的第三人称 -s形式) n.[生化]羧肽酶","carboxypolymethylene":"[化] 羧聚乙烯","carboxypolypeptidase":"[化] 羧基多肽酶\\n[医] 羧基多肽酶","carboy":"n. (外有木箱保护的)小口大玻璃瓶\\n[化] 酸坛; 小口玻璃瓶","carboys":"(carboy 的复数) n. (外有木箱保护的)小口大玻璃瓶\\n[化] 酸坛; 小口玻璃瓶","carbozaotine":"[建] 克布索丁","carbro":"[医]彩色照片，碳溴印像法","carbromal":"阿大林, 二乙代溴乙酰脲","carbs":"(carb 的复数) n. [汽车]汽化器","carbubarb":"[化] 卡布比妥","carbuncle":"n. 痈, 红玉, 红榴石\\n[医] 痈","carbuncled":"a. 用红玉的","carbuncles":"n. 红榴石, 红宝石, 痈( carbuncle的复数形式 )","carbuncular":"a. 红玉的, 红宝玉的\\n[医] 痈的","carbunculosis":"[医] 痈病","carburan":"铀铅沥青, 碳铀矿, 含铀烃","carburant":"n. 渗碳剂,增碳剂,碳化剂","carburate":"[建] 渗碳, 汽化","carburation":"[建] 渗碳(作用)(内燃烧内之)汽化(作用)","carburator":"[化] 渗碳器; 汽化器","carburelant":"[建] 增碳剂","carburesttor":"[机] 汽化器","carburet":"vt. 使与碳化合, 使渗碳\\n[医] 碳化物","carburetant":"n. 渗碳剂,增碳剂,碳化剂","carbureted":"v. 使与碳化合, 增碳( carburet的过去式和过去分词 )","carbureter":"[化] 汽化器; 化油器","carbureting":"v. 使与碳化合, 增碳( carburet的现在分词 )","carburetion":"n. 与碳化合, 混以碳氢化合物等","carburetor":"[化] 增碳器; 汽化器; 化油器","carburets":"vt. 使与碳化合, 增碳（carburet的第三人称单数形式）","carburetted":"v. 使与碳化合, 增碳( carburet的过去式和过去分词 )","carburetter":"[化] 汽化器; 化油器\\n[医] 增碳器, 汽化器(内燃机)","carburetting":"[建] 增碳","carburettor":"n. 汽化器","carburettors":"n. <机>汽化器, 化油器( carburettor的复数形式 )","carburise":"vt. [主英国英语] = carburize","carburite":"[化] 碳混铁","carburization":"n. 渗碳","carburize":"[建] 渗碳","carburized":"a. 渗碳的\\nv. 使渗碳（carburiz的过去式）","carburizei":"[机] 渗碳剂","carburizer":"渗碳剂[器]","carburizes":"vt. 使渗碳于…","carburizing":"[机] 渗碳","carbusintering":"渗碳烧结","carbutamide":"[化] 氨磺丁脲\\n[医] 磺胺丁脲, 依凡诺","carbuterol":"[化] 卡布特罗","carby":"[人名] 卡比","carbyl":"[化]二价碳基","carbylamine":"n. [化]胩","Carbyne":"燕麦灵","carcajou":"n. [动]狼獾","carcake":"n. ( 苏格兰某些地方在四旬斋开始之前一日吃的) 烘糕","carcanet":"n. <古>有珠饰(或金饰)的领子(或束发带),金项圈","carcas(plies)":"[化] 帘布层","carcase":"n. 尸体, 架子","carcases":"(carcase 的复数) n. 尸体, 架子","carcasing":"(carcase 的现在分词) n. 尸体, 架子","carcass":"n. 尸体\\n[医] 屠体(宰后除脏的畜体)","carcassed":"(carcass 的过去分词) n. 尸体\\n[医] 屠体(宰后除脏的畜体)","carcasses":"n. （动物的）尸体( carcass的名词复数 ); 烹调过的禽鸟骨骼","carcassing":"预埋管线工程","Carcassonne":"n. (Carcassonne)人名；(法)卡尔卡索纳","Carcassonne's":"[医] 卡尔卡索恩氏韧带(尿道三角韧带)","carcassonnes":"n. 卡尔卡松薄呢","Carcel":"卡索(法国曾经用过的一种发光强度单位。1卡索约等于10国际烛光)","carcenet":"[气]卡塞内特风","carcerular":"小坚果群的","carcerulus":"[植]小坚果群","Carcharhinidae":"n. [鱼] 真鲨科；白眼鲛科","carcharhinus":"[医]真鲨","Carcharias":"[网络] 大白鲨；噬人鲨；锥齿鲨属","Carchariidae":"白眼鲨科","carcharodon":"[医]噬人鲨","Carchemish":"n. 卡尔凯美什","carcholin":"(=carbachol)卡可林, 氯酰胆碱","carciag":"羊巴贝西虫病","carcin-":"[医]癌","carcinectomy":"n. 癌切除术\\n[医] 癌切除术","carcinelcosis":"[医] 癌性溃疡","carcinemia":"[医] 癌血症, 癌性恶病质","Carcinides":"绿泳蟹","carcino-":"pref. 癌\\n[医] 癌","carcinocidin":"消癌菌素","carcinoembryonic":"[医]癌胚的","carcinogen":"n. 致癌物质\\n[化] 致癌物","carcinogene":"致癌基因","carcinogenesis":"n. 致癌作用, 癌发生\\n[医] 致癌作用, 癌发生","carcinogenic":"a. 致癌作用, 癌发生\\n[医] 致癌的","carcinogenicity":"[医] 类癌瘤","carcinogenics":"(carcinogenic 的复数) a. 致癌作用, 癌发生\\n[医] 致癌的","carcinogenophore":"致癌基","carcinogens":"n. 致癌物( carcinogen的复数形式 )","carcinogensis":"致癌作用","carcinoid":"a. 良性肿瘤的\\nn. 良性肿瘤","carcinoids":"(carcinoid 的复数) adj.良性肿瘤的\\nn. 良性肿瘤","carcinologist":"甲壳动物学家, 癌学家","carcinology":"n. [动]蟹学","carcinolysin":"溶癌素","carcinolysis":"[化] 癌溶解\\n[医] 癌细胞溶解","carcinolytic":"[医] 溶癌的","carcinoma":"n. 癌\\n[医] 癌","carcinoma-in-situ":"[医]原位癌","carcinomas":"n. 癌","carcinomata":"n. 癌","carcinomatoid":"[医] 癌样的","carcinomatophobia":"[医] 癌病恐怖","carcinomatosis":"n. [医]癌扩散","carcinomatous":"[医] 癌的","carcinomectomy":"[医] 癌切除术","carcinomelcosis":"[医] 癌性溃疡","carcinomycin":"[化] 癌霉素\\n[医] 癌霉素","carcinophilia":"嗜癌性","carcinophilic":"[医] 嗜癌的","carcinophobia":"癌病恐怖","carcinophylin":"[医] 嗜癌素","carcinopolypus":"[医] 癌性息肉","carcinosarcoma":"n. 癌肉瘤","carcinosarooma":"癌肉瘤","carcinosectomy":"[医] 癌切除术","carcinosis":"[医] 多发性癌, 癌病, 癌","carcinostatic":"制癌的","carcinostatin":"抑癌菌素","carcinotron":"[电]回波管","carcinous":"癌性的","carclazyte":"白土, 高岭土, 陶土","carcolepsy":"","carcoma":"[医] 树屑样颗粒(热带居民粪便中)","carcoplasm":"肌浆","card":"n. 卡片, 纸牌, 节目单, 明信片, 梳棉机\\nvt. 备置卡片, 记于卡片上, 梳理\\n[计] 卡片, 卡","card-carrier":"n. 持有卡片者, 正式党员或会员","card-carrying":"a. 持会员证的, (非正式)彻底的, 真正的","card-holder":"持卡人；[计] 卡片夹；名片盒","card-holders":"(card-holder 的复数) 持卡人；[计] 卡片夹；名片盒","card-house":"n. 必然失败的计划；势必倒塌的建筑","card-index":"vt. 把...制作卡片索引","card-indexes":"(card-index 的复数) vt. 把...制作卡片索引","card-issuer":"发卡单位","card-issuers":"(card-issuer 的复数) 发卡单位","card-player":"n. 玩牌的人","card-players":"(card-player 的复数) n. 玩牌的人","card-playing":"n. 玩扑克牌","card-reader":"读卡机, 读卡器","card-readers":"(card-reader 的复数) 读卡机, 读卡器","card-sharp":"n. 打牌时经常作弊的人","card-sharper":"n. 打牌时经常作弊的人","card-sharps":"(card-sharp 的复数) n. 打牌时经常作弊的人","carda":"abbr. Continental Airborne Reconnaissance for Damage Assessment (USAF) 用于评估毁坏程度的大陆航空勘测（美国空军）","cardaissin":"[化] 牛副肾素","cardamine":"n. 碎米荠属植物","cardamom":"[医] 豆蔻, 小豆蔻","cardamoms":"(cardamom 的复数) [医] 豆蔻, 小豆蔻","cardamomum":"[医] 豆蔻, 小豆蔻","cardamon":"n. 小豆蔻[的种子]","cardamone":"[人名] 卡达蒙","cardamum":"n. 小豆蔻[的种子]","Cardan":"n. 万向接头","cardanol":"[化] 腰果酚; ┐如酚","cardassian":"n. 卡达西","cardboard":"n. 薄纸板\\n[化] 咭纸; 特等纸板; 卡纸板; 卡片纸板","cardboards":"(cardboard 的复数) n. 薄纸板\\n[化] 咭纸; 特等纸板; 卡纸板; 卡片纸板","cardcase":"n. 名片盒","cardcastle":"n. 势必倾倒的建筑，即将失败的计划","carde":"abbr. Canadian Armament Research and Development Establishment 加拿大武器研究与发展","cardea":"卡尔迪亚","carded":"a. 经过梳毛机梳过的","cardell":"[人名] 卡德尔","cardelmycin":"(=novobiocin)新生霉素","carden":"n. (Carden)人名；(英)卡登","cardenal":"[医]Phenobarbital","cardenas":"[人名] 卡德纳斯","cardenolides":"强心甾","carder":"n. 梳刷的人, 起毛工人","carders":"(carder 的复数) n. 梳刷的人, 起毛工人","cardew":"卡迪尤","cardfile":"[计] 卡片盒","cardfotomy":"[医] 贲门切开术, 心切开术","cardguide":"插件导轨","cardholder":"n. 持有信用卡的人,持有正式成员证的人,(持卡可获得某种权利的)持卡人","cardholders":"(cardholder 的复数) n.持有信用卡的人,持有正式成员证的人,(持卡可获得某种权利的)持卡人","cardhouse":"n. 势必倒塌的建筑，必然失败的计划","cardi":"pref. 开襟羊毛衫；心脏","cardia":"n. 贲门\\n[医] 贲门, 心窝, 心口(旧名)","cardia-":"[医] 心","cardiac":"n. 心脏病患者, 强心剂, 健胃药\\na. 心脏的, (胃的)贲门的","cardiacs":"(cardiac 的复数) n. 心脏病患者, 强心剂, 健胃药\\na. 心脏的, (胃的)贲门的","cardiaeraphy":"[医] 心动描记法","cardiagra":"[医] 心痛风","cardial":"[医] 贲门的","cardialgia":"n. 胃灼痛, 心痛","cardiameter":"[医] 贲门位置测量器","cardiamine":"[化] 强心胺","cardiamorphia":"[医] 心畸形","cardianastrophe":"[医] 心异位, 右位心","cardianesthesia":"[医] 心感觉缺失","cardianeuria":"心力不足","cardianeurysma":"心动脉瘤","cardiant":"[医] 心兴奋剂","cardiantia":"[建] 强心剂, 心兴奋剂","cardiaopath":"心病患者","cardiaplegia":"[医] 心麻痹, 心瘫痪","cardiasthenia":"[医] 心神经衰弱","cardiasthma":"[医] 心病性气喘","cardiataxia":"心搏失调","cardiatelia":"心发育不全","cardiauxe":"[医] 心扩大","cardiazol":"[化] 卡地阿唑\\n[医] 卡地阿唑, 米特腊唑, 次戊基四唑(强心剂)","cardicentesis":"[医] 心穿刺术","cardicin":"卡氏菌素","cardiechema":"[医] 心音","cardiectasis":"[医] 心扩张","cardiectomized":"[医] 心[部分]切除的","cardiectomy":"n. 心部分切除术, 贲门切除","cardielcosis":"贲门溃疡","cardiemphraxis":"[医] 心脏阻塞","cardies":"(cardy 的复数)  [人名] [康沃尔人、英格兰人姓氏] 卡迪 Cardew的变体","cardiethmoliposis":"[医] 心脏纤维脂肪沉着症","cardiette":"[医] 轻便心电图描记器(商品名)","cardieurysma":"[医] 心扩大, 心扩张","cardiff":"n. 加的夫（英国港市）","cardiff-by-the-sea":"[地名] [美国] 滨海加的夫","cardigan":"n. 卡迪根式开襟羊毛衫","cardigans":"n. 毛衣, 羊毛衫( cardigan的复数形式 )","Cardiganshire":"n. 卡的根郡(威尔士西部一郡)","cardigin":"[医] 卡迪京, 洋地黄毒甙","Cardiidae":"[网络] 鸟蛤科；鸟尾蛤科；乌蛤科","cardilate":"赤藓醇四硝酸酯","cardillat":"[法]卡迪拉特呢","cardiloid":"赤藓醇四硝酸酯","cardin":"[医] 牛心浸膏","cardinal":"n. 红衣主教, 鲜红色\\na. 主要的, 深红色的","cardinalate":"n. 红衣主教之职","cardinale":"[人名] 卡迪纳尔","cardinalfish":"[医]天竺鲷","cardinali":"[人名] 卡尔迪纳利","cardinalis":"[医]蝶铰部（软体动物）","cardinality":"[计] 基数","cardinally":"最重要地\\n基本地","cardinals":"n. 红衣主教( cardinal的复数形式 ); 红衣凤头鸟（见于北美, 雄鸟为鲜红色）; 基数","cardinalship":"n. 红衣主教之职位或任期","cardindex":"vt.将…制成卡片索引,将…记入卡片","cardine":"维斯纳丁；氢吡豆素","cardines":"cardo的复数","carding":"n. (毛、棉等的)梳理\\n[建] 起毛, 起绒","cardings":"(carding 的复数) n. (毛、棉等的)梳理\\n[建] 起毛, 起绒","cardinophyllin":"[化] 抗癌霉素","cardinosternal":"轴唇腹的","cardio":"n. 有氧运动\\npref. 表示心","cardio-":"pref. 心\\n[医] 心","cardio-accelerator":"[医] 心动加速剂","cardio-active":"[医] 作用于心脏的","cardio-angiography":"[医] 心血管造影术","cardio-angiology":"[医] 心血管学","cardio-aortic":"[医] 心主动脉的","cardio-arterial":"[医] 心动脉的","cardio-augmentor":"[医] 心脏促进的","cardio-inhibitory":"[医] 心动抑制的","cardio-omentopexy":"[医] 心网膜固定术","cardio-vascular":"adj. 心血管的","cardioacceleration":"心动加速; 加速心率","cardioacceleratory":"a. 使心动加速的","cardioactivator":"心脏激活器","cardioactive":"a. (药物等)作用于心脏的","cardioangiography":"心血管造影术","cardioblast":"[动]成心肌细胞","cardiocairograph":"[医] 心选择性显影机","cardiocele":"[医] 心突出","cardiocentesis":"心脏穿刺术","Cardioceras":"心菊石属","cardiochalasia":"贲门弛缓; 贲门松弛","cardiocinetic":"[医] 促心动的, 强心剂","cardiocirculatory":"a. 心脏和循环系统的","cardiocirrhosis":"[医] 心性肝硬变","cardioclasis":"[医] 心破裂","cardiodemia":"脂肪心","cardiodilator":"[医] 贲门扩张器","cardiodiosis":"[医] 贲门扩张术","cardiodynamics":"[医] 心[脏]动力学","cardiodynia":"n. [医]心痛, 胸痛","cardiodysesthesia":"[医] 心[脏]感觉失调","cardiodysneuria":"[医] 心[脏]神经机能失调","cardiodystrophia":"[医] 心营养不良","cardiogenesis":"[医] 心脏发生","cardiogenic":"a. 心原性的, 心脏发生的\\n[医] 心原性的, 心脏发生的","cardiogmus":"[医] 心脏痛, 心绞痛, 心动脉瘤","cardiogram":"n. 心电图\\n[医] 心动图, 心动描记曲线","cardiograph":"n. 心电图\\n[医] 心动描记器","cardiographed":"(cardiograph 的过去分词) n. 心电图\\n[医] 心动描记器","cardiographic":"[医] 心动描记的","cardiography":"[医] 心动描记法","cardiohepatic":"[医] 心肝的","cardiohepatomegaly":"[医] 心肝肿大","cardiohyperplasia":"[医] 心组织增生","cardioid":"n. [数]心形线\\na. 具有心脏形状的","cardioinhibitor":"心动抑制剂","cardioinhibitory":"[医]心动抑制的","cardiokinetic":"促心动的","cardiokinetlc":"[医] 促心动的, 强心剂","cardiokymograph":"心搏记纹鼓","cardiokymography":"[医] 心动记波法","cardiol":"abbr. cardiolith 心脏病专家; cardiologist(ic)(al)(ly) 心脏病专家的（地）; cardiology 心（脏）病学; cardiolysin 溶心肌素","cardiolipin":"心磷脂, 双磷脂酰甘油","cardiolith":"[医] 心石","cardiologic":"a. cardiology的变形","cardiological":"a. 心脏病学的","cardiologist":"n. 心脏病学家\\n[医] 心[脏]病学家","cardiologists":"(cardiologist 的复数) n. 心脏病学家\\n[医] 心[脏]病学家","cardiology":"n. 心脏病学\\n[医] 心[脏]病学","cardiolysin":"溶心肌素","cardiolysis":"[医] 心松解术, 心崩解","cardiomalacia":"[医] 心肌软化","cardiomegalia":"[医] 心肥大","cardiomegaly":"n. 心脏肥大\\n[医] 心肥大","cardiomelanosis":"[医] 心[脏]黑变(心肌黑色素沉着)","cardiomensurator":"[医] 测心仪","cardiomentopexy":"[医] 心网膜固定术","cardiometer":"n. 心能测量器, 心力计\\n[医] 心力测量器, 心力计","cardiometry":"[医] 心力测量法","cardiomotility":"[医] 心脏活动, 心脏移动","cardiomyoliposis":"[医] 心肌脂变","cardiomyopathy":"n. 心肌病","cardiomyopexy":"[医] 心肌固定术","cardiomyotomy":"[医] 贲门肌切开术","cardionecrosis":"[医] 心坏死","cardionector":"[医] 心动调节结构","cardionephric":"[医] 心肾的","cardioneural":"[医] 心神经的","cardioneurosis":"[医] 心神经机能病, 心神经衰弱","cardiopalmus":"[医] 心悸, 心跳","cardiopaludism":"[医] 疟疾性心脏病","cardiopath":"[医] 心[脏]病患者","cardiopathia":"[医] 心[脏]病","cardiopathic":"[医] 心[脏]病的","cardiopathology":"[医] 心脏病理学","cardiopathy":"n. [医]心脏病","cardiopericardiopexy":"[医] 心心包固定术","cardiopericarditis":"[医] 心心包炎","cardiophobe":"心脏病恐怖症患者","cardiophobia":"[医] 心脏病恐怖","cardiophone":"心音听诊器","cardiophonogram":"心音图","cardiophonograph":"心音图机","cardiophonography":"[医] 心音描记法","cardiophony":"[医] 心音听诊, 心音扩大","cardiophrenia":"[医] 心血管神经衰弱","cardiophtosia":"心下垂","cardioplasty":"[医] 贲门成形术","cardioplegia":"[医] 心麻痹, 心瘫痪","cardiopneumatic":"[医] 心肺的","cardiopneumograph":"[医] 心肺运动描记器","cardiopneumonopexy":"[医] 心肺叶固定术","cardioptosia":"[医] 心下垂","cardioptosis":"[医] 心脏下垂, 伦莫氏病","cardiopulmonary":"a. 心肺的\\n[医] 心肺的","cardiopuncture":"[医] 心穿刺术","cardiopyloric":"[医] 贲门幽门的","cardioregulatory":"心脏调节的","cardiorenal":"[医] 心肾的","cardiorespiratory":"a. 心和肺的, 心脏呼吸的\\n[医] 心脏呼吸的","cardioroentgenogram":"[医] 心[脏]X线照片","cardioroentgenography":"[医] 心[脏]X线照相术","cardiorrhaphy":"心脏修补术, 心肌缝合术","cardiorrhexis":"[医] 心破裂","cardioschisis":"心松离术","cardiosclerosis":"n. [医]心硬化","cardioscope":"n. [医]心脏检查器, 心脏镜","cardiospasm":"贲门痉挛","Cardiospermum":"[网络] 心孢子虫","cardiosphygmogram":"心动脉搏图","cardiosphygmograph":"[医] 心动脉搏描记器","cardiosphygmography":"心动脉搏描记法","cardiosplenopexy":"心脾固定术","cardiostenosis":"[医] 心腔狭窄","cardiostimulator":"[电] 心脏激发器","cardiosurgery":"[医] 心脏外科学","cardiosymphysis":"[医] 心粘合(心全部与胸壁粘合)","cardiotachometer":"n. [医]心动计数器,心率计","cardiotherapy":"[医] 心[脏]病疗法","cardiothoracic":"心胸的","cardiothyrotoxicosis":"[医] 心甲状腺中毒病","cardiotocograph":"分娩监护仪","cardiotomy":"n. [医]心切开术, 贲门切开术","cardiotonic":"a. 强心的, 强心剂\\nn. 强心的, 强心剂","cardiotopometry":"心浊音区测定法","cardiotoxic":"a. [医]心脏中毒的","cardiotoxin":"[化] 心脏毒素; 眼镜蛇毒素","cardiotrauma":"[医] 心脏外伤","cardiotrophotherapy":"[医] 心病营养疗法","cardiovalvulitis":"心瓣炎; 瓣性心内膜炎","cardiovalvulotome":"[医] 心瓣刀","cardiovalvulotomy":"[医] 二尖瓣切开术, 心瓣膜分离术","cardiovascular":"a. 心血管的\\n[医] 心血管的","cardiovascular-renal":"[医] 心血管肾的","cardiovasology":"心血管学","cardiovectography":"[医] 心电向量描记法","cardioversion":"n. [医]心律转变法,复律法","cardioverter":"n. [医]心律转变器, 复律器","cardiovertor":"心脏复律器","cardipaludis":"[医] 疟疾性心脏病","cardipericarditis":"[医] 心心包炎","cardiss":"[人名] 卡迪斯","carditis":"n. 心脏炎\\n[医] 心炎","Cardium":"n. 鸟蛤属\\n[网络] 贲门；心蛤","cardizem":"[医]地尔硫卓，合心爽，硫氮卓酮，哈氮卓，恬尔心[抗心绞痛药]","cardless":"[计] 无卡片的","cardmember":"n. 信用卡持有者","cardmembers":"(cardmember 的复数) n. 信用卡持有者","cardo":"n. [动]轴节,阳(茎)基环","cardol":"[医] 卡多耳(5-十五碳二烯间苯二酚)","cardon":"耙吸式挖泥船","cardona":"[地名] [菲律宾、乌拉圭、西班牙] 卡尔多纳","cardoncillo":"食用仙人掌","cardone":"[人名] 卡多内","cardoon":"n. 刺菜蓟","cardoso":"卡多苏（巴西直辖市）","cardosonite":"纤绿磷铁矿","Cardox":"卡尔道克斯爆破筒","cardoza":"[人名] 卡多萨","Cardozo":"n. (Cardozo)人名；(葡、英)卡多佐；(西)卡多索\\n卡多佐","cardphone":"n. 磁卡电话","cardphones":"(cardphone 的第三人称 -s形式) n. 磁卡电话","cardplayer":"n. 玩牌的人","cardplaying":"n. 玩(扑克)牌","cardpuncher":"n. 打孔机;打孔员","cardroom":"n. 桥牌室","cards":"n. (playing cards)(正式)一副纸牌, 一副扑克牌, 纸牌游戏, 打扑克","cardsase":"[医] 乙氧苯唑胺","cardsharp":"n. 打牌常作弊者","cardsharper":"n. 以诈赌纸牌为生者","cardston":"[地名] [加拿大] 卡兹顿","Carducci":"卡尔杜齐(Giosue, 1835-1907, 意大利诗人, 曾获1906年诺贝尔文学奖)","Carduelis":"[网络] 金翅雀属；金翅属；黑头红金翅雀","cardura":"卡度雷","Carduus":"[网络] 飞廉属；节毛飞廉；飞廉属植物","Cardwell":"n. (Cardwell)人名；(英)卡德韦尔","cardy":"[人名] [康沃尔人、英格兰人姓氏] 卡迪 Cardew的变体","care":"n. 小心, 照料, 忧虑\\nvi. 关心, 介意\\nvt. 在意, 喜欢","care-free":"a. 无忧无虑的, 舒畅的, 愉快的","care-laden":"a. 忧心忡忡的","care-leaver":"护理毕业生","care-leavers":"(care-leaver 的复数) 护理毕业生","care-taker":"n. 看管人, 暂时行使职权者, 暂时行使职权的政府或个人","care-takers":"(care-taker 的复数) n. 看管人, 暂时行使职权者, 暂时行使职权的政府或个人","carebaria":"[医] 头重感","carecloth":"n. (中世纪时婚礼上)罩在新婚夫妇头上的丝绸(或亚麻布)","cared":"v. 关心( care的过去式和过去分词 ); 担心; 在乎; 介意","cared-for":"关心","careen":"vt. 倾斜, 倾, (为了修理或清洁)使倾侧\\nn. 船的倾侧","careenage":"n. 倾船, 修船处","careened":"v. 将船倾侧, 将船倾倒（以清洗、捻缝或修理）( careen的过去式和过去分词 ); 倾斜; 倚靠; <美>（车辆）歪歪斜斜地行驶","careening":"v. 将船倾侧, 将船倾倒（以清洗、捻缝或修理）( careen的现在分词 ); 倾斜; 倚靠; <美>（车辆）歪歪斜斜地行驶","careens":"v. 将船倾侧, 将船倾倒（以清洗、捻缝或修理）( careen的第三人称单数 ); 倾斜; 倚靠; <美>（车辆）歪歪斜斜地行驶","career":"n. 事业, 生涯, 成功\\n[法] 职业, 专业, 履历","career-oriented":"adj. 与将来的事业相关的","careered":"vi. 全速前进, 猛冲（career的过去式与过去分词形式）","careering":"vi. 全速前进, 猛冲（career的现在分词形式）","careerism":"n. 野心, 追求名利","careerist":"n. 妄想发迹的人, 野心家\\n[法] 妄想发迹者, 野心家","careerists":"n. 妄想发迹的人, 一心追求名利地位的人, 野心家( careerist的复数形式 )","careerman":"n. 野心家,专业人员","careers":"n. 职业生涯；事业；职业（career的复数）","carefree":"a. 无忧无虑的, 不负责的","carefreeness":"n. carefree的变形","careful":"a. 小心的, 谨慎的","carefully":"adv. 小心地, 谨慎地","carefulness":"n. 小心, 仔细, 慎重","caregiver":"n. 照料者, 护理者","caregivers":"照顾者；看护人（caregiver的复数）","careinophilia":"[医] 嗜癌性","careirs":"abbr. Conservation and Renewal Energy Inquiry and Referral Service 保存和更新能量调查和咨询业务","Carel":"n. (Carel)人名；(法、荷、芬、南非)卡雷尔","careladen":"a. 多烦的, 忧心的","careless":"a. 粗心的, 不关心的, 无忧无虑的","carelessly":"adv. 不注意地, 粗心地","carelessness":"n. 粗心大意","careline":"（公司的）产品咨询热线, 服务热线, 客服热线","carelli":"[人名] 卡雷利","Caren":"n. 卡伦(f.)","carencro":"[地名] [美国] 凯林克罗","carene":"n. 四旬斋(旧时由主教规定给教士、俗人或由修道院院长规定给修道士的斋戒,共40天,在此期间只许吃面包,喝水)","carentan":"[地名] [法国] 卡朗唐","careol":"[建] 香苇醇","careotrypanosis":"[医] 南美洲锥虫病, 恰加斯氏病","carer":"n. 负责照顾（老人, 病人, 小孩）的人","carers":"n. （亲属中）护理病人者, 照顾老人者( carer的复数形式 )","cares":"（等于Central Advisory Referral Service）中心咨询服务","caress":"n. 爱抚, 拥抱\\nvt. 爱抚, 抱, 宠爱","caressed":"v. 爱抚或抚摸…( caress的过去式和过去分词 )","caresser":"n. caress的变形","caresses":"n. 爱抚, 抚摸( caress的名词复数 )\\nv. 爱抚或抚摸…( caress的第三人称单数 )","caressing":"a. 爱抚的, 亲切的, 表现爱情的","caressingly":"adv. 爱抚地, 亲切地","caressive":"a. 似爱抚的, 亲柔的","caressively":"adv. caress的变形","careswell":"[人名] 凯尔斯韦尔","caret":"n. 脱字符\\n[计] ^符号","caretake":"vt.照管, 看管","caretaker":"n. 照顾者, 看管者, 看守人\\n[法] 看守员, 管理员, 看管人","caretakers":"n. 看门人( caretaker的复数形式 )","caretakes":"(caretake 的第三人称 -s形式) vt.照管, 看管","caretaking":"看管","Caretta":"[网络] 蠵龟属；汐留海龟大楼；汐留的海龟大楼","Carettochelyidae":"两爪鳖科","Carew":"n. (Carew)人名；(英)卡鲁","careworn":"a. 忧心忡忡的","carex":"n. 苔属植物","carey":"n. 凯里（等于Cary）","carf":"abbr. 复康设备鉴定委员会（Commission on Accreditation of Rehabilitation Facilities）；中央飞行高度保留功能（Central Altitude Reservation Function）","carfare":"n. 车资","Carfax":"n. <英>(4条或4条以上道路的)交叉路口","carfonal":"吗乙氧苯","carful":"n. 一车之量","carfusin":"[医] 卡福辛, 石炭酸品红涂剂","cargador":"n. 搬运工,监督畜群装运者","cargage":"[法] 货运费","cargentos":"[医] 弱蛋白银(成药)","cargile":"[人名] 卡吉尔","Cargill":"n. 美国嘉吉公司","cargo":"n. 货物\\n[经] 货柜","cargo-cargo":"回头货","cargo-owner":"货主, 托运人","cargo-ship":"[水运][船] 货船","cargo-ships":"(cargo-ship 的复数) [水运][船] 货船","cargoboat":"n. 货船","cargoes":"n. （船或飞机装载的）货物( cargo的名词复数 ); 大量, 重负","cargoliner":"大型货运专机","cargoplane":"运输（飞）机","cargos":"(cargo 的复数) n. 货物\\n[经] 货柜","cargotainer":"集装箱","cargutocin":"[化] 卡古缩宫素","carhart":"[人名] 卡哈特","carhemoglobin":"碳酸血红朊","carhetus":"中直线","carhop":"n. 把饭菜端给汽车乘客的服务员","cari":"n. (Cari)人名；(法、意)卡里\\nabbr. 民航医学研究所（civil aeromedical researchinstitute）","Caria":"n. (Caria)人名；(西、意、葡)卡里亚","Cariama":"[网络] 卡里亚马","Cariamidae":"n. [鸟] 叫鹤科","carian":"n. (Carian)人名；(法)卡里安","carians":"(carian 的复数) n. (Carian)人名；(法)卡里安","cariated":"龋柱的, 骨疽的","carib":"n. 加勒比人（南美洲东北部的印第安人）；加勒比语","Cariban":"a. 加勒比人的, 加勒比语的","Caribbean":"n. 加勒比海\\na. 加勒比海的, 加勒比人的","caribbeans":"n. 加勒比海( Caribbean的名词复数 )","Caribbee":"n. & adj.加勒比人(的)","caribe":"n. 水虎鱼；南美洲的一种食人鱼","Caribees":"[网络] 加勒比人","caribi":"[医] 流行性坏疽性直肠炎","Caribosireninae":"加勒比海牛亚科","caribou":"n. 北美驯鹿","caribous":"n. （北美洲产的）驯鹿( caribou的复数形式 )","caribs":"(carib 的复数) n. 加勒比人（南美洲东北部的印第安人）；加勒比语","carica":"[医]番木瓜","Caricaceae":"n. [植] 番木瓜科","caricaturable":"a. 适于被讽刺的","caricatural":"a. 讽刺画的, 滑稽的","caricature":"n. 讽刺画, 漫画, 漫画手法\\nvt. 画成漫画讽刺","caricatured":"v. 用漫画表现或夸张描述、模仿…( caricature的过去式和过去分词 )","caricatures":"n. 漫画( caricature的名词复数 ); 夸张的描述或模仿; 漫画艺术; 滑稽或讽刺的模仿艺术\\nv. 用漫画表现或夸张描述、模仿…( caricature的第三人称单数 )","caricaturing":"v. 用漫画表现或夸张描述、模仿…( caricature的现在分词 )","caricaturist":"n. 讽刺画家, 漫画家","caricaturists":"n. 讽刺画家, 漫画家( caricaturist的复数形式 )","carices":"carex的复数","caricin":"番木瓜苷","Caricom":"abbr. 加勒比共同市场（Caribbean Community and Common Market）","caricous":"[医] 无花果状的","caridean":"n. 囊虾总目","caried":"(cary 的过去分词) n. 卡里（男子名）","caries":"n. 龋, 骨疡\\n[医] 龋, 骨疡, 骨疽","carignane":"佳利酿(酿酒葡萄品种名)","carillon":"n. 排钟, 钟乐\\n[电] 钟乐器","carillonneur":"n. 钟琴演奏师","carillons":"n. 钟琴；钟乐；钟乐器\\nn. (Carillon)人名；(法)卡里永","carimbose":"卡林糖","carin":"[人名] 卡林; [地名] 山口（索马里语）","carina":"n. 隆线\\n[医] 隆凸","carinae":"隆线,嵴,突(复数)","carinal":"龙骨板","carinamide":"卡林酰胺, 苄磺胺苯酸, 对苄磺酰胺基苯甲酸","carinate":"a. 有龙骨形的\\n[医] 隆凸的, 船骨状的","carinated":"a. = carinate；(陶器)有棱纹的","carination":"[医] 嵴状, 船骨状","carinatus":"[医]具龙骨瓣； 具龙骨状突起的","carindacillin":"[化] 卡印西林; 羧茚苄青霉素","caring":"a. 有同情心的；表示或感到关怀或关心的","carini":"[地名] [意大利] 卡里尼","carinimurate":"有脊网壁, 具突网脊","Carinomidae":"龙首科","Carinthia":"n. 卡林西亚（奥地利南部的州）","carinthian":"a. , n. Carinthia的变形","carinthians":"(carinthian 的复数) adj., n. Carinthia的变形","carinthine":"亚蓝闪石","carinula":"(pl.carinulae ) 小隆线, 小隆骨","carinulate":"具隆线的","cario":"n. 开罗（埃及首都）","carioca":"n. 克力欧卡舞","Cariocan":"n. (巴西)里约热内卢之居民","cariocas":"n. （巴西的）卡里奥克舞( carioca的名词复数 )","cariogenic":"a. 生龋齿的","cariogenici":"[医] 生龋的","cariogenicity":"生龋性","cariole":"n. 小型马车, 雪橇","carionecrosis":"骨疽性坏死","cariopside":"颖果","cariopsis":"颖果","cariose":"(=carious)腐烂了的","cariosity":"n. 龋, 蛀牙","cariostatic":"a. 止龋的","cariou":"[人名] 卡里乌","carious":"a. 龋的, 骨疡的, 腐烂的\\n[医] 龋的","CARIS":"计算机辅助情报检索系统","Carisel":"卡里赛尔地毯布","carisoprodate":"肌安宁","carisoprodol":"n. [药]异丙基甲丁双脲,肌安宁(镇痛及骨骼肌松弛药)","carissa":"[人名] 卡丽莎","carissima":"<意> n.亲爱的(用于称呼女子)","carissin":"[医] 假虎刺甙","carissone":"[建] 假虎刺酮","Carita":"n. (Carita)人名；(法、意、葡)卡里塔","caritas":"n. 博爱","caritative":"a. 博爱的","carithers":"[人名] 卡里瑟斯","caritinoid":"(=Carotenoid)胡萝卜素","caritive":"残缺的, 残缺格","caritol":"卡里托耳(成药, 一种含胡萝卜素的溶液)","carius":"[人名] 卡里乌斯","carjack":"车辆起重器","carjacked":"(carjack 的过去分词)  车辆起重器","carjacker":"n. 武力劫夺汽车；抢劫司机财物 (carjacking的变形)","carjackers":"(carjacker 的复数) n. 武力劫夺汽车；抢劫司机财物 (carjacking的变形)","carjacking":"n. 劫车","carjackings":"(carjacking 的复数) n. 劫车","cark":"n. 烦恼, 忧虑\\nv. (使)烦恼, (使)忧虑","carked":"vt. 使…烦恼；使…忧虑\\nvi. 烦恼；忧虑\\nn. 烦恼；忧虑","carking":"a. 恼人的, 烦人的","carks":"vt. 使…烦恼；使…忧虑\\nvi. 烦恼；忧虑\\nn. 烦恼；忧虑","Carl":"n. 卡尔（男名）","carla":"n. 卡拉（女子名）","carlberg":"[人名] 卡尔伯格","carle":"n<古>.乡下人, 老粗","carlee":"[人名] 卡莉","carleen":"[人名] 卡琳","carlen":"[人名] 卡伦","carlene":"[人名] 卡林","carles":"[人名] 卡莱斯","carless":"a. 没有汽车的,无车的,没有被提供汽车","carlet":"n. 三面锉","Carleton":"n. 卡尔顿（位于加拿大）；卡尔顿大学","carletonville":"[地名] [南非共和国] 卡尔顿维尔","carley":"n. 卡利救生筏","carli":"[人名] 卡利，卡莉（女名）","carlie":"[人名] 卡莉","carlilagin":"[医] 软骨素原","Carlile":"n. (Carlile)人名；(英)卡莱尔","carlin":"n. 老妇人；巫婆","Carlina":"n. (Carlina)人名；(西)卡利娜","carline":"n. 女人, 老太婆","carliner":"[人名] 卡利纳","carling":"n. 短纵梁","carlings":"n. 纵梁, 支甲板横梁的纵梁\\nn. (Carling)人名；(瑞典)卡林；(英、挪)卡林","carlino":"n. (Carlino)人名；(意)卡利诺","carlinville":"[地名] [美国] 卡林维尔","carlisle":"n. 卡莱尔（英国英格兰西北部城市）","Carlism":"n. 拥护卡洛斯争取西班牙王位者","Carlist":"n. 拥护卡洛斯争取西班牙王位者","Carlists":"(Carlist 的复数) n.拥护卡洛斯争取西班牙王位者","Carlite":"一种(镀于硅钢片上的)绝缘层","carlito":"n. (Carlito)人名；(法、葡)卡利托","carlitz":"[人名] 卡利茨","carll":"[人名] 卡尔","carlo":"n. 卡洛（男子名）","carload":"n. 车辆荷载, 货车的最低载重量\\n[经] 车辆载荷, 整车, (铁路)货车每辆积载量","carloader":"装车机","carloading":"n. 以铁路货车数计算的货物运入量, 以铁路货车数计算的货物运出量","carloadings":"[复]n.装车数","carloads":"(carload 的复数) n. 车辆荷载, 货车的最低载重量\\n[经] 车辆载荷, 整车, (铁路)货车每辆积载量","carlock":"[人名] 卡洛克; [地名] [美国] 卡洛克","carlos":"n. 卡洛斯（男子名）","carlostite":"柱星叶石","carlot":"n. (=carload lot)达法定最低载重量之货物","carlota":"卡洛塔（1840～1927, 墨西哥皇后, 马克西米连皇帝之妻）","Carlotta":"n. 奕香（法国著名香水品牌）；卡洛塔（女子名）","Carlovingian":"a. 加洛林王朝(法兰克王国的第二个王朝)的","Carlow":"n. 卡罗（人名）","Carlowitz":"n. 奥地利产的红葡萄酒","carlquist":"[人名] 卡尔奎斯特","carls":"[人名] 卡尔斯","Carlsbad":"n. 卡尔斯巴德（美国新墨西哥州东南部城市）","Carlsberg":"n. 嘉士伯啤酒公司；嘉士伯啤酒","carlsen":"n. (Carlsen)人名；(英、西、丹、挪、瑞典)卡尔森","carlsmith":"[人名] 卡尔史密斯","Carlson":"n. 卡尔森（公司名）；卡尔松（姓氏）","Carlsruhe":"卡尔斯鲁厄","Carlsson":"n. (Carlsson)人名；(英、西)卡尔森；(丹、瑞典)卡尔松","carlstadt":"n. (Carlstadt)人名；(德)卡尔施塔特","carlston":"[人名] 卡尔斯顿","carlton":"n. 卡尔顿（男子名, 姓氏）","carlucci":"[人名] 卡卢奇","carly":"n. 卡莉（女子名）","Carlyle":"n. 卡莱尔","Carlylean":"a. (苏格兰散文作家和历史学家)卡莱尔的","Carlylese":"n. (苏格兰散文作家和历史学家)卡莱尔(式)的文风(常指模仿卡莱尔风格的文风)","carm":"n. (Carm)人名；(西、瑞典)卡姆\\nabbr. 回旋自动谐振脉塞","carma":"卡玛（女子名）","carmacin":"[医] 卡马辛(成药,含碳酸钙镁等)","carmack":"[人名] 卡马克","carmagnole":"(1789-1794 年法国革命派所着的)一种翻领短上衣","carmaker":"n. 汽车制造商","carmakers":"n. 汽车制造商（carmaker的复数）；汽车制造厂","carmalum":"卡红明矾染液","carman":"n. 运货马车的车夫, 电车司机","Carmarthen":"n. 喀麦登（威尔士一郡）","Carmarthenshire":"卡马森郡[英国威尔士原郡名]","carmatron":"具有宽广调谐范围的振荡器","Carmazine":"代森锰锌杀菌剂","carme":"n. [天文]木卫十一","CARMEL":"n. 卡梅尔(f.)","carmel-by-the-sea":"[地名] [美国] 滨海卡梅尔","carmela":"n. 卡梅拉（女子名）","carmelina":"人名；(意)卡尔梅利纳","carmelita":"n. 卡梅丽塔（女子名, Carmela的昵称）","Carmelite":"n. (天主教)加尔默罗会修士","Carmelites":"(Carmelite 的复数) n. (天主教)加尔默罗会修士","Carmella":"n. 卡梅拉(f.)","carmelo":"n. (Carmelo)人名；(西、葡)卡梅洛；(意、马耳他)卡尔梅洛\\n卡梅洛","carmeloite":"[建] 伊丁玄武岩","carmen":"n. 卡门（女子名）","Carmet":"卡梅特","carmi":"[地名] [美国] 卡迈","Carmichael":"n. 卡米高（地区名）；卡迈克尔（人名）","carmichaeline":"卡米车灵, 卡鸟碱","carmin":"[人名] 卡明","carmina":"n. (Carmina)人名；(意)卡尔米纳；(西、葡)卡米纳","carminate":"(=carminated)洋红色的, 胭脂红色的, 胭脂红酸盐","carminated":"[医]卡红色的, 胭脂红色的, 洋红色的","carminative":"a. 排出胃肠气体的\\nn. 驱风止痛剂","carmine":"n. 胭脂红, 洋红色, 深红色\\na. 胭脂红的, 洋红色的, 深红色的","carminite":"n. [矿]砷铅铁矿","carminomycin":"洋红霉素","carminophil":"嗜卡红的","carminophile":"[医] 嗜卡红的","carmintive":"[建] 驱风剂, 排气剂","carminum":"卡红, 胭脂红","carmo":"[地名] [巴西] 卡尔穆","carmody":"n. (Carmody)人名；(英)卡莫迪","carmofur":"[化] 卡莫氟; 氟己嘧啶","carmoisine":"红色酸性染科","carmona":"n. (Carmona)人名；(意、葡、法)卡尔莫纳；(西)卡蒙娜","carmot":"n. (炼金术士认为的)构成点金石的原料","Carmowax":"聚乙二醇","carmus":"球茎","carmustine":"亚硝(基)脲氮芥, 卡氯芥, 双氯乙基亚硝脲","Carn":"堆石标记","Carnaby":"Street<英>卡纳比街(伦敦的一条街道,以时装出名), (年轻人的)时装","carnac":"[人名] 卡纳克; [地名] [法国] 卡尔纳克","carnadine":"麝香石竹, 康耐馨","carnage":"n. 大屠杀, 残杀","carnahan":"[人名] 卡纳汉","carnal":"a. 肉体的, 肉欲的\\n[医] 肉的, 肉欲的","carnalise":"[网络] 肉体","carnalism":"n. 寻欢作乐, 纵欲主义","carnalist":"n. 声色之徒, 纵欲者","carnality":"n. 肉欲, 好色\\n[法] 肉欲, 好色, 淫荡","carnalize":"v. 好色","carnalized":"vt. 好色；沉湎于肉欲","carnalizing":"vt. 好色；沉湎于肉欲","carnallite":"n. 光卤石(钾的原料), 砂金卤石","carnallitite":"[化] 光卤石","carnally":"adv. 肉体地, 世俗地","Carnap":"卡纳普（人名）","carnapper":"n. 专偷汽车的贼","carnaria":"食肉动物","Carnarvon":"n. 卡那封郡(位于威尔斯), 卡那封(该郡之首府)","Carnarvons":"(Carnarvon 的复数) n.卡那封郡(位于威尔斯), 卡那封(该郡之首府)","Carnarvonshire":"卡那封郡[英国威尔士原郡名]","carnassial":"a. 食肉的","carnatio":"肉色","carnation":"n. 康乃馨, 粉红色\\n[医] 肉色, 天然肉色","carnationed":"n. 肉色, 粉红色；【植物】麝香石竹,康乃馨 (Dianthus caryophyllus)\\na. 肉红色的, 粉红色的","carnations":"n. 麝香石竹, 康乃馨( carnation的复数形式 )","carnauba":"n. [植]巴西棕榈(所产硬腊可用于制造上光腊,唇彩,唱片等)","carnaubanol":"[医] 巴西棕榈醇, 二十四烷醇","carnaubon":"肾磷脂","carnaval":"n. （法）嘉年华会；狂欢节","carne":"n. 肉（西班牙语）","carneal":"[人名] 卡尼尔","carneau":"[动]卡尔诺鸽","carnegie":"n. 卡内基（姓氏）","Carnegiea":"[网络] 巨人柱属；仙人掌科巨人柱属；北美洲巨人柱是巨人柱属","carnegieite":"[矿]三斜霞石","carnegine":"(=pectenine)卡乃京, 二甲基沙尔苏林碱","carneiro":"[地名] [巴西] 卡尔内鲁; [地名] [美国] 卡尼罗","carnelian":"n. 红玉髓, 光玉髓\\n[化] 光玉髓; 肉红玉髓","carnelians":"(carnelian 的复数) n. 红玉髓, 光玉髓\\n[化] 光玉髓; 肉红玉髓","carnell":"[人名] [英格兰人姓氏] 卡内尔职业名称，石弓手，来源于盎格鲁诺曼底法语，含义是“城垛，射击孔”(battlement,embrasure); [人名] [英格兰人姓氏] 卡内尔 Carbonell或Cardinal的简称","carneolutescin":"肉黄菌素, 肉色青霉菌素","carneose":"(=carneous, corneus)肉色","carneous":"a. 似肉的, 肉色的","carner":"[人名] 卡纳","carnes":"[医]肌肉","carnesale":"[人名] 卡恩塞尔","carnet":"n. <法>官方证明信件,车票簿","carnevale":"[人名] 卡内瓦莱","carney":"v. 哄骗\\nn. 哄骗的话","Carnian":"[地质]喀尼阶","carnidazole":"[化] 卡硝唑","carnie":"n. 游乐场,游乐场管理员(游客)","Carniferrin":"[医] 肉铁质","carniferrol":"卡尼佛罗耳(成药, 含铁制剂)","carnifex":"刽子手","carnification":"n. 肉质化","carnificial":"a. 刽子手的, 屠夫的","carnified":"[医]肉质化的","carnifies":"vt. 使成肉质；使变成肉质\\nvi. 变成肉质","carnify":"vt. 使成肉质\\nvi. 变成肉质","carnifying":"vt. 使成肉质；使变成肉质\\nvi. 变成肉质","carnigen":"卡尔尼银(成药, 肉组织浸膏)","carnillionyx":"红白带纹玛瑙(缠丝玛瑙)","carnine":"肌苷, 次黄嘌呤核苷","Carniola":"n. (Carniola)人名；(意)卡尔尼奥拉","carniole":"多孔白云岩","carnism":"肉食癖, 肉食过多","carnitas":"[网络] 猪肉丝；卡尼塔斯；是一道菜","carnitine":"[化] 卡尼汀; 肉碱; 肉毒碱\\n[医] 肉毒硷, 三甲基羟基丁酰甜菜硷","carnival":"n. 嘉年华会, 狂欢节, 饮宴狂欢","carnivalesque":"a. 好像过节的, 快乐的","carnivals":"n. 狂欢节( carnival的复数形式 ); 嘉年华会; 激动人心的事物的组合; 五彩缤纷的颜色组合","Carnivora":"[pl. ][拉]食肉类","carnivore":"n. 食肉动物\\n[医] 食肉动物, 食虫植物","carnivores":"n. 食肉动物, 食虫植物( carnivore的复数形式 )","carnivorism":"[植]食虫","carnivority":"食肉性","carnivorous":"a. 食肉的\\n[医] 食肉的","carnivorousness":"n. carnivorous的变形","carnochan":"[人名] 卡诺坎","carnography":"暴力镜头, 对暴力的描绘","Carnophobia":"[医] 肉食恐怖","carnosaur":"肉食龙（掠食性大型恐龙, 前肢短）","Carnosaura":"[网络] 食肉动物","carnosaurs":"(carnosaur 的复数)  肉食龙（掠食性大型恐龙, 前肢短）","carnose":"a. 肉的","carnosine":"[生化]肌肽","carnosinemia":"肌肽血","carnosity":"[医] 赘肉","carnosol":"卡诺醇","Carnot":"n. (Carnot)人名；(法)卡诺；(葡)卡诺特\\n卡诺","carnotite":"n. 钒钾铀矿\\n[化] 钒钾铀矿","carnotization":"卡诺(循环)化","carnous":"a. 肉的","carnoustie":"[地名] [英国] 卡诺斯蒂","carnoy":"[人名] 卡诺努瓦","Carns":"(Carn 的复数) 堆石标记","carnulose":"稍具肉质的","carnutine":"[医] 卡纽丁, α-羟基-γ-三甲基丁基甜菜硷","carny":"vt. 哄骗\\nn. (流动)游艺场","caro":"[医] 肌, 肉","caro-":"[建] 肉","caroa":"(=coroa, crua, curaua)[巴西]卡罗阿叶纤维","carob":"n. 角豆树\\n[医] 卡罗布胶, 角豆胶","caroba":"玫瑰木叶","carobbite":"方氟钾石","carobine":"[医] 玫瑰木硷","carobone":"驱梅树叶脂","Carobronze":"磷青铜","carobs":"n. 长豆角( carob的复数形式 )","caroche":"n. 十六,七世纪之一种豪华马车","caroched":"n. (17世纪赴盛会用的)华丽马车[亦作 caroch]","caroff":"[人名] 卡罗夫","caroid":"[医] 卡罗伊德(成药,一种消化性散剂)","carol":"n. 颂歌, 欢乐的歌\\nv. 歌颂, 欢唱","carol(l)ite":"[化] 硫铜钴矿","carola":"n. 卡罗拉（女名）","Carolan":"[日]卡罗纶(醋酯长丝、短丝)","Carolans":"(Carolan 的复数) [日]卡罗纶(醋酯长丝、短丝)","carolathine":"不纯粘土","carole":"n. 卡罗尔（女子名）","carolean":"a. 英国查理一世或二世的","caroled":"v. 欢乐地唱( carol的过去式和过去分词 ); 唱圣诞颂歌","caroler":"n. 欢唱（颂歌）的人","carolers":"n. 欢唱（颂歌）的人( caroler的名词复数 )","caroli":"n. (Caroli)人名；(法、意、罗)卡罗利","Carolina":"n. 北(或南)卡罗来纳州","Carolinas":"n. 美国南北卡罗莱纳州（Carolina的复数）","caroline":"n. 凯若琳（女子名）","carolines":"abbr. Caroline Islands (Kusaie, Palau, Ponape, Truk, Yap) in the Western Pacific 位于西太平洋中的卡罗琳岛（库塞群岛，帕劳群岛，旁纳裴群岛，特鲁克群岛，雅浦岛）","caroling":"v. 欢乐地唱( carol的现在分词 ); 唱圣诞颂歌","Carolingian":"a. 卡洛林王朝的\\nn. 卡洛林王朝的帝王","Carolingians":"(Carolingian 的复数) a. 卡洛林王朝的\\nn. 卡洛林王朝的帝王","Carolinian":"n. 美国北[南]卡罗莱纳州人","carolinic":"[建] 肉灵酸","carolite":"(=carrollite)硫铜钴矿","caroll":"v. 欢唱;唱颂歌赞美","carolled":"v. 欢乐地唱( carol的过去式和过去分词 ); 唱圣诞颂歌","caroller":"卡罗尔(女子名)[亦作 Carole,Karol]","carollers":"(caroller 的复数) 卡罗尔(女子名)[亦作 Carole,Karol]","carolling":"v. 欢乐地唱( carol的现在分词 ); 唱圣诞颂歌","carols":"n. 圣诞颂歌; 圣诞之歌, （宗教）颂歌( carol的名词复数 )\\nv. 欢乐地唱( carol的第三人称单数 ); 唱圣诞颂歌","carolus":"[人名] 卡罗勒斯","caroluses":"n. (Carolus)人名；(英)卡罗勒斯；(法)卡罗吕斯","carolyn":"n. 卡洛琳（女子名）","carom":"n. 连着双球的一击, 碰击而反跳\\nvi. 一击连撞二球, 碰击而反跳","caromed":"v. <美>碰击弹回, 一击连撞二球, 碰击而反跳( carom的过去式和过去分词 )","caroming":"v. <美>碰击弹回, 一击连撞二球, 碰击而反跳( carom的现在分词 )","caroms":"n. 连撞两球, 连击( carom的名词复数 )\\nv. <美>碰击弹回, 一击连撞二球, 碰击而反跳( carom的第三人称单数 )","caron":"n. 卡朗（法国一香水品牌）；卡洛（电影演员）","carona":"[地名] [瑞士、意大利] 卡罗纳","caronamide":"[医] 卡龙酰胺, 对苄磺酰氨基苯甲酸, 卡林酰胺","carondelet":"[地名] [厄瓜多尔] 卡龙德莱特","carone":"蒈酮, 5-蒈酮","caroni":"[地名] [特立尼达和多巴哥] 卡罗尼","caronnyl-monothio-acid":"[建] 一硫赶碳酸","carosella":"色拉茴香","caroset":"法兰绒","carosidine":"卡绕西定","carosine":"卡绕素","carosis":"熟睡","carosso":"[人名] 卡罗索","carota":"(pl. carotae )胡萝卜","carotenase":"[医] 胡萝卜素酶","carotene":"n. 胡萝卜素\\n[化] 胡萝卜素; 叶红素","carotenemia":"[医] 胡萝卜素血[症]","carotenes":"(carotene 的复数) n. 胡萝卜素\\n[化] 胡萝卜素; 叶红素","carotenodermia":"[医] 胡萝卜素黄皮病","carotenogenesis":"[建] 葫萝匐素形成作用","carotenoid":"n. 类胡萝卜素\\n[化] 类胡萝卜素; 类叶红素","carotenoids":"(carotenoid 的复数) n. 类胡萝卜素\\n[化] 类胡萝卜素; 类叶红素","carotenol":"[化] 胡萝卜醇; 叶黄素\\n[医] 胡萝卜素醇","carotenosis":"[医] 胡萝卜素[色素]沉着, 皮橙色病","carothers":"[人名] [苏格兰人姓氏] 卡罗瑟斯 Carruthers的变体","carotic":"a. 迷睡的\\n[医] 迷睡的","caroticoclinoid":"[医] 颈动脉翼突的","caroticotympanic":"[医] 颈[动脉]鼓的","carotid":"n. 颈动脉\\na. 颈动脉的","carotidal":"a. 颈动脉的 (carotid的变形)","carotids":"(carotid 的复数) n. 颈动脉\\na. 颈动脉的","carotidynia":"[医] 颈动脉痛","carotin":"n. (=carotene)[生化]胡罗卜素","carotinaemia":"[医] 胡萝卜素血[症]","carotinase":"胡萝卜素酶","carotine":"[医] 胡萝卜素","carotinemia":"[医] 胡萝卜素血[症]","carotinoid":"[生化]类胡罗卜素","carotinoidemia":"胡萝卜素类血症","carotinosis":"皮橙色病","carotis":"[医] 颈动脉","carotodynia":"[医] 颈动脉痛","carotol":"[化] 胡萝卜醇","carotovoricin":"胡萝卜软腐欧氏菌素","carotte":"胡萝卜","caroubier":"角豆树","carousal":"n. 喧闹的酒宴","carousals":"(carousal 的复数) n. 喧闹的酒宴","carouse":"n. 喧闹的酒会或宴会\\nvi. 痛饮, 畅饮","caroused":"v. 痛饮, 闹饮欢宴( carouse的过去式和过去分词 )","carousel":"n. 竞技比武大会","carousels":"n. 喧闹的酒会; 旋转木马( carousel的复数形式 )","carouser":"n. 大喝大闹的人","carouses":"v. 痛饮, 闹饮欢宴( carouse的第三人称单数 )","carousing":"v. 痛饮, 闹饮欢宴( carouse的现在分词 )","carousingly":"adv. carouse的变形","caroverine":"[化] 卡罗维林","caroxazone":"[化] 卡罗沙酮","carp":"n. 鲤鱼\\nvi. 吹毛求疵, 挑剔","carp-":"vi. 吹毛求疵\\nn. 鲤鱼\\nn. (Carp)人名；(罗)卡尔普；(英、葡、瑞典)卡普","carp-like":"a. carp的变形","carpaccio":"n. (配有调味汁的) 生牛肉片, 白汁红肉 , 擅用红白两色而得名","carpaine":"[化] 番木瓜碱\\n[医] 番木瓜硷","carpal":"a. 腕的\\nn. 腕骨","carpale":"n. 腕骨\\n[医] 腕骨","carpalia":"n. 腕骨 (carpale的变形)","carpals":"[医]腕骨","carpamone":"萘氧乙酸钠","carpark":"停车场","carparks":"(carpark 的复数)  停车场","carpas":"abbr. Comisin Asesora Regional de Pesca para el Atlantico Sud-Occidental （西班牙语）西南大西洋渔业咨询委员会; Regional Fisheries Advisory Commission for the South-West Atlantic 西南太平洋区域渔业咨询委员会（代号）","Carpathian":"a. 喀尔巴阡山脉的","Carpathians":"(=Carpathian Mountains)(中欧)喀尔巴阡山脉","carpathite":"黄地蜡","carpe":"n. 鲤鱼；木工铅笔","carpectomy":"[医] 腕骨切除术","carped":"v. 挑剔, 吹毛求疵, 找茬儿( carp的过去式和过去分词 )","carpel":"n. 心皮\\n[医] 心皮(植物)","carpellary":"心皮的","carpellate":"a. 具有心皮的","carpellotaxy":"心皮序列","carpellum":"心皮","carpels":"(carpel 的第三人称 -s形式) n. 心皮\\n[医] 心皮(植物)","carpen":"[医]Carbenicllin","Carpene":"多果定","Carpentaria":",Gulf of卡奔塔利亚湾(靠澳大利亚东北部)","carpenter":"n. 木匠","carpentered":"(carpenter 的过去时) n. 木匠","carpenteria":"卡彭特虫属","carpentering":"n. 木匠, 木工\\nvi. 当木匠, 做木匠工作\\nvt. 制作\\nn. (Carpenter)人名；(英、葡、法)卡彭特","carpenters":"n. 木工, 木匠( carpenter的名词复数 )","carpenterworm":"毛毛虫","carpentry":"n. 木工手艺, 木工业, 木器","carper":"n. 吹毛求疵者, 苛评者","carpers":"(carper 的复数) n. 吹毛求疵者, 苛评者","carperter":"n. 木工","carpes":"(carpe 的复数) n. 鲤鱼；木工铅笔","carpet":"n. 地毯, 地毯状物\\nvt. 铺以地毯, 铺盖","carpet-bagger":"没有地方基础的议员","carpet-baggers":"(carpet-bagger 的复数) 没有地方基础的议员","carpet-bomb":"对（某地）实行地毯式轰炸","carpet-bombing":"n. 地毯式轰炸","carpetbag":"n. 毯制的旅行袋","carpetbagger":"n. (美)南北战争后只带一个旅行袋去南方投机谋利的北方人, 非本地区的政客","carpetbaggers":"n. 美国内战后利用南方不定局势谋利的人( carpetbagger的复数形式 )","carpetbaggery":"n. 美国南北战争后利用南方不稳定的局势投机谋利的人 (carpetbagger的变形)","carpetbagging":"(carpetbag 的现在分词) n. 毯制的旅行袋","carpetbags":"n. 毯制的旅行袋( carpetbag的名词复数 )\\nv. 毯制的旅行袋( carpetbag的第三人称单数 )","carpeted":"vt. 在…上铺地毯（carpet的过去式与过去分词形式）","carpeting":"n. 地毯料, 地毯","carpetings":"(carpeting 的复数) n. 地毯料, 地毯","carpetless":"a. 没有铺地毯的","carpets":"n. 地毯（carpet的复数）","carpette":"小地毯","carpettes":"(carpette 的复数) 小地毯","carpetweed":"n. 粟米草","carphenazine":"[化] 丙酰奋乃静","carpholite":"[矿]纤锰柱石","carphologia":"(=carphology)摸索, 摸空, 捉空摸床, 用手紧握被盖的现象","carphology":"n. 摹空","Carphophis":"[网络] 脑膜炎","carphosiderite":"[矿]草黄铁矾","carphostilbite":"杆沸石","carpi":"腕","Carpinaceae":"[网络] 科","carpincho":"水猪皮, 水猪皮手套革","carping":"a. 吹毛求疵的, 挑毛病的","carpino":"[人名] 卡尔皮诺; [地名] [意大利] 卡尔皮诺","carpinteria":"[地名] [美国] 卡平特里亚","Carpinus":"鹅耳枥属","carpio":"[地名] [美国、西班牙] 卡皮奥","carpipramine":"[化] 卡匹帕明","carpitis":"[医] 腕关节炎","carpitron":"卡皮管","carpo-":"[前缀]表示“果实”之义","Carpobrotus":"[网络] 食用昼花属；剑叶花属","carpocace":"腕病","Carpocapsa":"n. 苹果蠹蛾","carpocarpal":"[医] 腕腕的","carpocerite":"触腕节","Carpodacus":"[网络] 朱雀属；金翅属；拉丁属名","carpodermis":"果皮","carpodes":"废心皮","carpogenic":"a. 生果实的,结果实的","carpogenous":"果上生的","Carpoglyphus":"[医] 果螨属","carpogone":"果胞(红藻)","carpogonial":"a. 果胞的","carpogonium":"n. 果胞\\n[医] 育胚器(子囊菌的雌性生殖器)","carpohylile":"干森林群落","Carpoidea":"海果纲","carpoids":"海果类","carpokyphosis":"[医] 腕后弯","carpolite":"n. 石子; 石籽","carpolith":"[医] 果石, 石化果实","carpological":"a. carpology的变形","carpologist":"n. 果实学家, 果实分类学家","carpology":"n. 果实学","carpomany":"心皮化","carpometacarpal":"[医] 腕掌的","carpometacarpus":"n. (鸟翅膀上的)腕掌骨","Carpomycetae":"果菌纲","carpool":"v. 合伙使用汽车","carpooled":"v. 汽车合用组织( car pool的过去式和过去分词 )","carpooler":"n. 合伙用车组织成员","carpooling":"v. 汽车合用组织( car pool的现在分词 )","carpools":"v. 汽车合用组织( car pool的第三人称单数 )","carpopedal":"[医] 腕足的","carpophagous":"a. 食果的","carpophalangeal":"[医] 腕指的","carpophilous":"蚀果的, 寄生于果实的","carpophore":"n. [植]心皮柄, 果瓣柄","Carpophthora":"[医] 毁果病毒属","carpophyll":"n. 大孢子叶","carpophyte":"孢堆果原植体, 显花植物, 大孢子植物, 种子植物","carpopodite":"腕节","carpoptosia":"腕下垂","carpoptosis":"[医] 腕下垂, 手垂症","carport":"n. 汽车棚","carposid":"番木瓜素","carposide":"[化] 番木瓜苷","carposoma":"(pl. carposomata)子实体柄的不孕部","carpospore":"n. 果孢子\\n[医] 果孢子(植)","carposporic":"a. carpospore的变形","carposporophyte":"果孢(子)体","carposporous":"a. carpospore的变形","carpostome":"孢囊口","carpostrote":"[植]果播","carpoxenia":"果实直感, 心皮直感","carppox":"[医] 鲤白斑病, 鲤痘","carprofen":"[化] 卡洛芬","carps":"n. 鲤鱼( carp的名词复数 ); 很挑剔的人\\nv. 挑剔, 吹毛求疵, 找茬儿( carp的第三人称单数 )","carpsucker":"n. [鱼]鲤形亚口鱼, 黑眼鲤形亚口鱼","carpule":"卡普耳(安瓿)","carpus":"n. 腕, 腕骨\\n[医] 腕","Carr":"n. 凯尔（挪威, 住在沼泽的人）","carrabassett":"[地名] [美国] 卡勒巴西特","carrabelle":"[地名] [美国] 卡拉贝尔","carrack":"n. 宽身帆船","carracks":"(carrack 的第三人称 -s形式) n. 宽身帆船","carradine":"[人名] 卡拉丹","carragceen":"n. 角叉菜","carragcheen":"n. 角叉菜","carrageen":"[建] 角叉菜, 鹿角菜","carrageenan":"n. [化]角叉(菜)胶","carrageenin":"n. [化]角叉(菜)胶","carragenates":"[化] 角叉酸盐; 角叉菜酸盐; 角菜酸盐","carragenines":"[化] 角叉苷; 角叉菜苷; 鹿角菜苷","carragheen":"n. (=cargeen)[植]角叉菜","carragheenin":"n. [化]角叉(菜)胶","carran":"[人名] 卡伦; [地名] [爱尔兰] 卡伦","Carranza":"n. (Carranza)人名；(西)卡兰萨","Carrara":"n. 卡拉拉（意大利地名）","carrasco":"n. (Carrasco)人名；(捷、英、法、西、葡)卡拉斯科","carratene":"胡萝卜素","carraway":"[人名] 卡拉韦","carre":"n. 卡雷（姓氏）","carreau":"[医] 腹肿硬","carrefour":"n. 十字路口, 广场","carreker":"[人名] 卡雷克","carrel":"n. (图书馆)小阅读室","carrell":"n. (Carrell)人名；(英、芬)卡雷尔\\n小单间\\n分隔式单人桌","carrels":"(carrel 的复数) n. (图书馆)小阅读室","carrene":"[有化]二氯甲烷","Carrera":"n. 卡雷拉（意大利的知名滑雪品牌）；豪雅赛车","Carreras":"(Carrera 的复数) n. 卡雷拉（意大利的知名滑雪品牌）；豪雅赛车","carrere":"[人名] 卡雷尔","carreres":"(carrere 的复数)  [人名] 卡雷尔","carres":"(carre 的复数) n. 卡雷（姓氏）","carret":"[人名] 卡雷特","carretera":"[地名] 公路（西班牙语）","carretta":"[人名] 卡雷塔","carrey":"[人名] 卡里","carrhae":"[地名] [土耳其] 卡雷（哈兰的旧称）","carriable":"a. 可携带的","carriacou":"[地名] [格林纳达] 卡里亚库岛","carriage":"n. 马车, 客车, 举止, 运输\\n[经] 搬运费, 运费","carriageable":"a. 手提的, 可通行马车的","carriageful":"n. 整整一马车","carriagepiece":"楼梯踏步梁","carriages":"n. （火车的）客车厢( carriage的复数形式 ); （旧时载客的）四轮马车; 运输; 举止","carriageway":"n. 车行道\\n[法] 车道, 马路","carriageways":"n. 车道, 马路( carriageway的复数形式 )","Carrick":"n. (=galleon)大帆船(15至18世纪初军舰商船两用的)","Carrickfergus":"卡里克弗格斯","carrico":"[人名] 卡里科","carrie":"n. 卡丽（女名, Caroline的昵称）","carried":"a. 入神的；被运的；忘我的","carrier":"n. 运送者, 邮递员, 带菌者\\n[计] 载波","carrier-and-stacker":"[化] 堆垛车","carrier-bag":"手提袋；购物袋","carrier-bags":"(carrier-bag 的复数) 手提袋；购物袋","carrier-based":"a. 以航空母舰为基地的, 舰载的","carrier-borne":"a. 舰载的","carrier-free":"[医] 无载体的, 不含载体的","carrier-nation":"n. 为别国代理海外贸易的国家","carrier-pellet":"[建] 催化剂载体片","carrierbased":"a. 以航空母舰为基地的, 舰载的","carriere":"[人名] 卡里尔","carriers":"n. （自身不受感染而传播疾病的）带菌者( carrier的复数形式 ); （尤指经营空运的）运输公司; 搬运人; 军输车","carries":"v. 传递；携带；运载；怀孕（carry的第三人称单数形式）","carrigan":"[人名] 卡里根","carrigans":"[地名] [爱尔兰] 卡里根斯","carrigg":"[人名] 卡里格","carril":"[地名] [阿根廷、西班牙] 卡里尔","carrillo":"n. [姓氏]卡里罗; [人名] 卡里略; [地名] [哥斯达黎加、墨西哥] 卡里约","Carrington":"n. (Carrington)人名；(英、西)卡林顿","carriogenicity":"[医] 生龋性","carriole":"n. 小单人马车, 小篷车, 狗拉的雪橇","carrion":"n. 死肉, 腐肉\\na. 腐肉的, 似腐肉的, 吃腐肉的","carrions":"(carrion 的复数) n. 死肉, 腐肉\\na. 腐肉的, 似腐肉的, 吃腐肉的","carris":"abbr. Companhia Carris de Ferro de Lisboa (Portuguese=Lisbon Street Railway) （葡萄牙语）里斯本市内电车道; Compannia Carris de Perro de Lisboa （葡萄牙语）里斯本电车公司","carrizo":"苔草芦苇；苔草色；苔类学家","carrle":"n. (Carrle)人名；(德)卡尔勒","carro":"[人名] 卡罗","carroccio":"n. (中世纪意大利各共和国)插有军旗的战车","carrol":"[人名] [英格兰人姓氏] 卡罗尔 Carroll的变体","carrol(l)ite":"[化] 硫铜钴矿","Carroll":"n. 卡罗尔（罗马人的姓）","Carrollese":"a. 具有(英国儿童文学作家)卡罗尔风格的","Carrollian":"a. 具有(英国儿童文学作家)卡罗尔风格的","Carrolline":"a. 具有(英国儿童文学作家)卡罗尔风格的","carrollite":"[矿]硫铜钴矿","carrolls":"[地名] [美国] 卡罗尔斯","Carrollton":"n. 卡罗敦（美国一城市）","carrom":"n. (carom之变体)连撞二球之一击, 撞击后弹回","carromata":"n. 畜力二轮车","Carron":"n. (Carron)人名；(英)卡伦；(法、西)卡龙","carronade":"n. 臼炮","carrot":"n. 胡萝卜\\n[医] 胡萝卜","carrot-and-stick":"a. （直译）胡萝卜加大棒的, （意译）威逼加利诱的","carrot-root":"[医] 胡萝卜","carrot-topped":"adj. 红头发的（头发颜色像胡萝卜的）","carrotene":"[医] 胡萝卜素","carrothers":"[人名] [苏格兰人姓氏] 卡罗瑟斯 Carruthers的变体; [地名] [美国] 卡罗瑟斯","carrotin":"[医] 胡萝卜素","carrots":"n. 胡萝卜；红萝卜（carrot的复数形式）","carrottop":"n. 红发的人","carrottopped":"n. [美国俚语]长红头发的人","carroty":"a. 胡萝卜色的, 红发的","carrouges":"[地名] [法国] 卡鲁日","carrousel":"n. 旋转木马","carrousels":"(carrousel 的复数) n. 旋转木马","Carrow":"n. (Carrow)人名；(英)卡罗","Carrs":"(Carr 的复数) n. 凯尔（挪威, 住在沼泽的人）","carrucate":"n. 卡勒凯特(旧时英国的土地丈量和估税单位,约合100英亩,但常据土质而不同)","carruth":"[人名] 卡鲁思","Carruthers":"n. (Carruthers)人名；(英)卡拉瑟斯","carry":"n. 进位, 射程, 运载\\nvt. 携带, 运送, 支持, 传送, 包含\\nvi. 被携带, 能达到\\n[计] 进位; 进位数","carry-back":"n. 亏损补报措施,抵前","carry-cot":"n. 手提式婴儿床","carry-forward":"n. 亏损预报措施，延后","carry-home":"a. <美>便于携带的","carry-in":"[经] 转入库存","carry-on":"n. 手提行李\\na. 手提的","carry-ons":"(carry-on 的复数) n. 手提行李\\na. 手提的","carry-out":"= takeaway","carry-outs":"(carry-out 的复数)  = takeaway","carry-over":"n. 遗留, 遗留物\\n[机] 夹带物","carry-scraper":"[化] 铲运机","carryall":"n. 一种四轮马车, 军用大轿车, 一种载客汽车, 大提包/箱, 轮式铲运机","carryalls":"单马马车, 旅行提袋( carryall的名词复数 )","carryback":"n. （上年度应税损益的）冲回（额）","carrycot":"n. 轻便婴儿床","carrycots":"n. <英>手提式婴儿床( carrycot的复数形式 )","carryforward":"亏损预报措施, 延后, 过次","carrying":"[法] 运载","carrying-on":"n. 手提行李\\na. 手提的","carrying-ons":"(carrying-on 的复数) n. 手提行李\\na. 手提的","carrying-pole":"n. 扁担","carryings":"(carrying 的复数) [法] 运载","carryings-on":"n. 愚蠢的行为, 轻率的行为","carryon":"n. 可随身携带的物品","carryophyllane":"[建] 石竹烷","carryout":"n. 供打包的酒菜","carryover":"n. 移后扣减；移行","cars":"abbr. 中美洲研究站（Central America Research Station）；计算机化自动额定值系统（computerized automatic rating system）；汽车收据结账证书（Certificates for Automobile Receivables）","carsal":"[计] 因果的","carsalam":"[化] 卡沙兰; 苯┭嗪二酮","carsality":"[计] 诱发性, 因果律","carse":"n. <苏格兰>(河边的)冲积平原","carsey":"n. <英俚>厕所","Carshalton":"n. 卡苏顿（位于伦墩郊区）","carsick":"a. 晕车的","carsickness":"n. 晕车","Carso":"n. (Carso)人名；(意)卡尔索","carson":"n. 卡尔森（姓氏, 男子名）","carsrud":"n. [姓氏]卡斯鲁德","carst":"喀斯特; 岩溶","Carstairs":"n. (Carstairs)人名；(英)卡斯泰尔斯","carstal":"卡斯醇, 胡萝卜萜醇","carstares":"[人名] 卡斯泰尔斯","carsten":"卡斯滕（人名）","carstens":"[人名] 卡斯滕斯","carstensen":"[人名] 卡斯滕森","carstone":"[建] 砂铁岩","Carswell":"n. (Carswell)人名；(英)卡斯韦尔","cart":"n. 二轮运货马车\\nvi. 驾运货马车\\nvt. 用车装载","cart-driver":"车把式","cart-horse":"拉货车的马","cart-horses":"(cart-horse 的复数) 拉货车的马","cart-load":"n. 一车之载量","cart-track":"（路面不平的）小路, 小径","cart-tracks":"(cart-track 的复数) （路面不平的）小路, 小径","cart-wheel":"n. 车轮；横翻筋斗；一元银币（美金）","cart-wheels":"(cart-wheel 的复数) n. 车轮；横翻筋斗；一元银币（美金）","carta":"n. （西）书信；纸牌","cartage":"n. 运输, 运费","cartage-in":"[经] 进货搬运费","cartage-out":"[经] 销货搬运费","Cartagena":"n. 卡塔赫纳","cartago":"n. (Cartago)人名；(西)卡塔戈","cartap":"巴丹","carte":"n. (附有价目的)菜单","carted":"vt. 用推车或卡车运送（cart的过去式与过去分词形式）","cartel":"n. 卡特尔, 企业联合, 俘虏交换条约, 决斗挑战书\\n[经] 同业联合, 联合贩卖, 卡特尔","cartelise":"vt., vi. [主英国英语] ＝ cartelize","cartelization":"卡特尔化","cartelize":"v. 组成卡特尔,组成企业联盟","cartellino":"[意]作品角上画出的姓名标记","cartels":"n. <经>卡特尔, 企业联合( cartel的复数形式 )","carteolol":"[化] 卡替洛尔","carter":"n. 运货马车夫","carteret":"n. (Carteret)人名；(法)卡尔特雷；(英)卡特里特","carterets":"(carteret 的复数) n. (Carteret)人名；(法)卡尔特雷；(英)卡特里特","carteron":"n. (Carteron)人名；(法)卡尔特龙","carterons":"(carteron 的复数) n. (Carteron)人名；(法)卡尔特龙","carters":"(carter 的复数) n. 运货马车夫","cartersville":"[地名] [美国] 卡特斯维尔","carterville":"[地名] [美国] 卡特维尔","Cartesian":"a. 笛卡尔的, 笛卡尔哲学的\\nn. 笛卡尔主义者","Cartesianism":"n. 笛卡儿哲学, 笛卡儿思想","Cartesians":"(Cartesian 的复数) a. 笛卡尔的, 笛卡尔哲学的\\nn. 笛卡尔主义者","cartful":"n. 一车的量","cartha":"[人名] 卡撒","Carthage":"n. 迦太基","Carthaginian":"a. 迦太基的\\nn. 迦太基人","Carthaginians":"(Carthaginian 的复数) a. 迦太基的\\nn. 迦太基人","Carthago":"<拉>=Carthage","carthame":"(用红花的干花瓣制成的)深红颜料, 红花素","carthamin":"[化] 红花素\\n[医] 红花素","carthamine":"[化] 红花素","Carthamus":"[网络] 红花属；红花族；红花黄色素","carthorse":"n. 拖货车的马","carthorses":"n. 拖货车的马, 干重活儿的马( carthorse的复数形式 )","Carthusian":"n. 天主教加尔都西会教士","Carthusians":"(Carthusian 的复数) n. 天主教加尔都西会教士","carthy":"[人名] 卡锡","cartialgenous":"n. 鹿茸","carticaine":"卡铁卡因(局麻药)","Cartier":"n. 卡蒂亚, 卡蒂埃（人名）\\n卡地亚（珠宝品牌）","cartiibust":"漫画家","cartilaage":"a. 脆骨","cartilage":"n. 软骨\\n[医] 软骨","cartilages":"n. <解>软骨( cartilage的复数形式 ); 软骨结构","cartilagin":"软骨蛋白","cartilagines":"[医] 软骨","cartilagineus":"[医] 软骨的","cartilaginification":"[医] 软骨化","cartilaginiform":"[医] 软骨样的","cartilaginoid":"[医] 软骨样的","cartilaginous":"a. [解剖]软骨的, 软骨质的","cartilago":"(=cartilagines)[解]软骨","cartilagotropic":"[医] 亲软骨的","cartimat":"自动精密坐标展点仪","cartinellin":"(=cortinellin)香菇菌素","carting":"运出","cartisane":"镶金银线花边","Cartland":"n. (Cartland)人名；(英)卡特兰","cartledge":"[人名] [英格兰人姓氏] 卡特利奇住所名称，来源于古诺斯语，含义是“多石地”(rocky ground)+古英语，或“多沼泽的溪流”(boggy stream)","cartlidge":"[人名] 卡特利奇","cartload":"n. 一车的载量, 大量","cartloads":"(cartload 的复数) n. 一车的载量, 大量","cartman":"n. 赶大车(或轻型二轮车)的人,卡车司机","cartmill":"[人名] [英格兰人姓氏] 卡特米尔 Cartmell的变体","cartney":"[人名] 卡特尼","carto":"abbr. 三维电解剖标测系统；西班牙凯图公司（国际著名的专业节能科技开发与应用推广企业）","cartoccio":"绘画、雕塑等艺术品上记载作者姓名等的小标牌","cartogram":"n. 统计地图\\n[医] 统计图","cartograph":"地图, (特指)插画地图","cartographer":"n. 地图制作者, 制图师","cartographers":"n. 制图者( cartographer的复数形式 )","cartographic":"[计] 制图的","cartographical":"a. 地[制] 图的","cartographically":"adv. cartographic的变形","cartography":"n. 地图制作, 制图学, 制图","cartogrphic":"a. 制图学的, 制图法的","cartological":"a. 地图学的, 海图学的","cartology":"n. 地图学, 海图学","cartomancy":"n. 纸牌卜卦","cartometry":"地图量算; 量图学","carton":"n. 硬纸盒, 纸板箱\\n[化] 卡纸","cartoner":"n. 纸板包装机","cartonful":"[网络] 纸箱","cartoning":"纸盒[箱]成形","cartons":"n. 尤指装食品或液体的)硬纸盒( carton的复数形式 ); 塑料盒; 硬纸盒（或塑料盒）所装物品; 纸板盒","cartoon":"n. 卡通画, 漫画\\nv. 画漫画","cartooned":"(cartoon 的过去分词) n. 卡通画, 漫画\\nv. 画漫画","cartooning":"(cartoon 的现在分词) n. 卡通画, 漫画\\nv. 画漫画","cartoonish":"a. 动画片似的","cartoonist":"n. 漫画家","cartoonists":"n. 漫画家( cartoonist的复数形式 )","cartoons":"n. 卡通动画；动漫图书（cartoon的复数）","cartop":"a. (大小和重量)可置于车顶上运送的","cartophily":"n. 集香烟牌子(一种爱好,指收集、整理并研究香烟盒内所附的画片)","cartopper":"n. 可放在汽车顶之小舟","cartose":"卡尔透斯(碳水化物混合液)","cartossin":"","cartouch":"n. 漩涡花饰, 弹药库","cartouche":"n. 涡卷饰, 椭圆形图形, 火药筒","cartouches":"n. 椭圆形轮廓；漩涡装饰；装饰镜板\\nn. (Cartouche)人名；(法)卡图什","Cartox":"混碳杀(环氧乙烷(10％)二氧化碳(90％)混合剂)","cartridge":"n. 弹药筒, 弹药, 一卷软片, 墨粉鼓\\n[计] 盒式磁带机","cartridges":"n. 子弹( cartridge的复数形式 ); （打印机的）墨盒; 录音带盒; （唱机的）唱头","cartroad":"un. 马路\\n[网络] 恰尔特罗阿德；乡村路；畜力车道","carts":"n. 购物车；手推车","cartularies":"n. 特许权登录簿, 房地产契据册, 档案保管处( cartulary的名词复数 )","cartulary":"n. 契据集, 契据登记簿","cartvision":"卷盘式电视","cartway":"n. ＝ cart-road","cartways":"(cartway 的复数) n. ＝ cart-road","cartwheel":"n. 车轮(货车的车轮), 侧手翻","cartwheeled":"n. 车轮；横翻筋斗；一元银币（美金）","cartwheeler":"n. 车轮；横翻筋斗；一元银币（美金） (cartwheel的变形)","cartwheeling":"n. 车轮；横翻筋斗；一元银币（美金）","cartwheels":"n. （大车）车轮( cartwheel的名词复数 ); 侧手翻, 侧身筋斗","cartwright":"n. 车匠","cartwrights":"(cartwright 的复数) n. 车匠","Carty":"卡蒂（人名）","carubicin":"[化] 卡柔比星; 洋红霉素","carubinose":"[化] 卡如宾糖; d-甘露糖","carucage":"n. (旧时英国的)犁头税, 每一卡勒凯特的土地税","carucate":"n. 卡勒凯特(旧时英国的土地丈量和估税单位,约合100英亩,但常据土质而不同)","carucates":"(carucate 的复数) n.卡勒凯特(旧时英国的土地丈量和估税单位,约合100英亩,但常据土质而不同)","carucci":"[人名] 卡鲁奇","carum":"[医] 藏茴香, ┓蒿","caruncle":"n. 种阜, 肉冠, 肉阜\\n[医] 小阜, 肉阜","caruncles":"(caruncle 的复数) n. 种阜, 肉冠, 肉阜\\n[医] 小阜, 肉阜","caruncula":"[医] 小阜, 肉阜","carunculae":"[医] 处女膜痕","caruncular":"肉冠\\n种阜\\n肉阜","carunculate":"[医]具种阜的","carunculated":"a. caruncle的变形","carunculous":"a. caruncle（肉髯, 皮瘤, 肉冠, 鸡的肉垂）的变形","carus":"[医] 昏厥","Caruso":"卡鲁索（人名）","caruth":"[人名] 卡鲁思","caruthers":"[人名] 卡拉瑟斯","carvacrol":"n. 香芹粉\\n[化] 香芹酚","carvacryl":"[化] 香芹基","carvacrylamine":"香芹胺","carvactyl":"香芹基","carval":"n. (爱尔兰曼岛的宗教主题的)民谣,赞美诗","carvalho":"n. (Carvalho)人名；(葡)卡瓦略","carvan":"高碳钒铁","carvasin":"[化] 硝酸异山梨酯","carve":"v. 雕刻, 切开","carve-built":"a. 外板平接(或镶)的","carve-out":"公司的某一部门独立出来成立新公司并在首次发行股票时出售部分股票的过程","carve-up":"n. 瓜分; 分赃","carved":"a. 有雕刻的","carvedilol":"[医]卡维地洛第三代β受体阻滞剂，具有非选择性扩张血管作用，用于心力衰竭治疗。","carvel":"(=caravel)n.轻快帆船","carvel-built":"a. 以平铺法钉造的,外板平接的","carvell":"[人名] [英格兰人、爱尔兰人姓氏] 卡维尔 Carvill的变体","carven":"caeve的过去分词","carvene":"[化] 香芹烯\\n[医] 藏茴香烯, 香芹烯","carvenol":"[化] 香芹烯醇","carvenone":"[化] 香芹烯酮\\n[医] 香芹烯酮","carveol":"香芹醇, 葛缕醇","carver":"n. 雕刻匠, 雕工, 切肉刀\\n[医] 雕刻器","carveries":"(carvery 的复数)  烤肉餐馆","carvers":"(carver 的复数) n. 雕刻匠, 雕工, 切肉刀\\n[医] 雕刻器","carvery":"烤肉餐馆","carves":"v. 切, 切碎( carve的第三人称单数 ); 雕刻; 艰苦创业, 奋斗取得（事业、名声等）","carvestrene":"非活性枞萜, 消旋枞油烯, 香芹萜","carveterpin":"香芹萜二醇","carveth":"[人名] 卡维思","carville":"卡维尔（人名）\\n卡维尔（地名）","carvin":"[人名] 卡文; [地名] [法国] 卡尔万","carving":"n. 雕刻品, 雕刻, 雕刻术","carvings":"n. 雕刻品（carving的复数）","carvoeila":"电气岩","carvol":"[化] 香芹酮\\n[医] 藏茴香酮, 香芹酮","carvomenthenol":"[化] 香芹聪醇","carvomenthol":"[医] 香芹薄荷醇, 异薄荷脑","carvomenthone":"葛缕薄荷酮","carvone":"香芹酮","carvotanacetone":"[医] 香芹艾菊酮, 异莳萝薄荷酮","carvoxime":"香芹(酮)肟","carwash":"洗车房；洗车处","carwell":"[地名] [澳大利亚] 卡韦尔","cary":"n. 卡里（男子名）","cary-":"n. 卡里（男子名）","Carya":"山核桃","caryatic":"a. caryatid的变形","caryatid":"n. 女像柱","caryatides":"n. 女像柱( caryatid的名词复数 )","caryatids":"n. 女像柱( caryatid的名词复数 )","caryatin":"山核桃黄素","caryclastic":"核破裂的","caryenchyma":"核液","caryin":"山核桃素, 毡毛山核桃素","caryinite":"砷锰铅矿","Caryl":"蒈烷基","carylamine":"[化] 蒈烷胺","caryle":"[人名] 卡里尔","caryo-":"为 karyo- 之变体","caryoblast":"[医] 成核细胞, 核胚细胞","Caryocaraceae":"n. 多柱树科；油桃木科","caryocerite":"褐稀土矿","caryochromatophil":"[医] 核嗜色的, 核嗜染性的","caryochrome":"核嗜色性","caryocinesia":"(间接)核分裂, 有丝分裂","caryocinesis":"有丝分裂, 核丝状分裂","caryocinetic":"[医] [间接]核分裂的, 有丝分裂的","caryoclasis":"[医] 核破裂","Caryococcus":"[医] 原虫核球菌属","caryogamic":"[医] 核配合的","caryogamy":"[医] 核配合","caryogenesis":"[医] 核生成","caryogenetics":"核遗传学","caryogenic":"[医] 核生成的, 核原的","Caryogonad":"小核, 生殖核","caryogram":"核型图, 染色体组型模式图","caryokinesis":"(间接)核分裂","caryolite":"肌结","caryolobic":"[医] [细胞]核分叶的","caryolobism":"(细胞)核分叶","caryology":"(细)胞核学","caryolymph":"核液","caryolysis":"(细胞)核溶解","caryolytes":"肌结","caryolytic":"[医] 核溶解的, 溶核的","caryomere":"染色体泡","caryomicrosome":"[医] 核微粒","caryomitome":"[医] 核网丝","caryomitosis":"间接核(有丝)分裂","caryomitotic":"[医] [间接]核分裂的, 有丝分裂的","caryomorphism":"[医] 核形","caryomycin":"核霉素","caryon":"(细胞)核","caryophag":"[医] 嗜核细胞, 嗜核体","Caryophanales":"显核细菌目","Caryophanon":"显核菌属","caryophil":"[医] 嗜噻嗪铵[染料]的","Caryophyllaceae":"[医] 石竹科","caryophyllaceous":"adj. 石竹科的","Caryophyllales":"石竹目","caryophyllene":"[化] 石竹烯\\n[医] 石竹烯, 丁香油烃","caryophyllenol":"[化] 石竹烯醇","caryophyllia":"佛手珊瑚","Caryophyllidae":"石竹亚纲","caryophyllin":"丁子香素, 石竹素","Caryophyllinae":"石竹目","caryophyllosis":"鲤蠢病","caryophyllus":"[医] 丁香, 丁子香, 鸡舌香","caryopilite":"肾硅锰矿","caryoplasm":"[医] 核质, 核浆","caryoplastin":"副染色质, 纺锤体丝质","caryopses":"n. 颖果；壳果 (caryopsis的变形)","caryopsis":"n. 颖果\\n[医] 颖果","caryorrhexis":"[医] 核破裂","caryosome":"染色质核仁, 双核仁, 核体","caryosphere":"核球","caryospherical":"[医] 核球的","Caryota":"[网络] 鱼尾葵属；摆尾棕榈；孔雀椰子属","caryotheca":"核膜","caryotin":"核质, 染色质","caryozoic":"核内寄生的","carzenide":"[化] 卡西尼特; 氨磺酰苯酸; 氨磺酰苯甲酸","carzey":"n. <英俚>厕所","carzinocidin":"(=carcinocidin)消癌菌素","carzinomycin":"n. 癌霉素\\n[化] 癌霉素","carzinophilin":"[医] 嗜癌素","carzinophillin":"嗜癌菌素","carzinostatin":"制癌菌素, 嗜癌素","cas":"abbr. 中国科学院（Chinese Academy of Sciences）；计算机技术学会（Computer Arts Society）；控制自动化系统（Control Automatic System）","casa":"abbr. 天文学高级研究中心（Centre for Advanced Study of Astronomy）；计算机与自动化系统（Computer and Automated System Association）；合作应用卫星A（Cooperative Application Satellite A）","casaba":"n. 卡萨巴甜瓜","Casablanca":"n. 卡萨布蓝卡","casady":"[人名] 卡萨迪","casal":"a. 有格的, 关于格的","casale":"[人名] 卡塞莱; [地名] 村（意大利语）","casals":"(casal 的复数) adj.有格的, 关于格的","casamassima":"[地名] [意大利] 卡萨马西马","casandra":"[人名] 卡桑德拉","Casanova":"n. 卡萨诺瓦式人物(意大利浪荡公子)","Casanovas":"(Casanova 的复数) n. 卡萨诺瓦式人物(意大利浪荡公子)","casao":"abbr. Chartered Accountants Students Association of Ontario 安大略湖特许会计研究者协会","casar":"n. (Casar)人名；(西)卡萨尔","casarella":"[人名] 卡萨雷拉","casares":"[地名] [阿根廷、尼加拉瓜、西班牙] 卡萨雷斯","casas":"(casa 的复数) abbr. 天文学高级研究中心（Centre for Advanced Study of Astronomy）；计算机与自动化系统（Computer and Automated System Association）；合作应用卫星A（Cooperative Application Satellite A）","casassa":"[人名] 卡萨萨","Casaubon":"n. (Casaubon)人名；(法)卡索邦","casava":"n. (cassava之变体)木薯属植物, 树薯粉","casazza":"[人名] 卡萨扎","casbah":"n. 阿拉伯式之宫廷","casca":"[建] 树皮","cascabel":"n. 炮的尾钮, 响尾蛇, 球形穿孔的铃","cascade":"n. 小瀑布, 瀑布状物\\nvi. 成瀑布落下\\n[计] 层叠, 级联","cascaded":"a. 级联的","cascades":"n. 小瀑布；叶棚（cascade的复数）","Cascadia":"卡斯卡底古陆","cascading":"[计] 级联","cascadite":"橄云煌岩","cascado":"牛丝虫病","cascais":"[地名] [葡萄牙] 卡斯凯什","cascalho":"n. (巴西一带含钻石或金的)砂石沉积物","cascalote":"卡斯卡洛特木","cascamite":"脲醛树脂与蛋白质混合的粘合剂","cascante":"[地名] [西班牙] 卡斯坎特","cascara":"n. 药鼠李\\n[化] 药鼠李; 药鼠李皮:波希鼠李皮","cascarilla":"n. [植]西印度苦香树(产于西印度群岛)","cascarillin":"[化] 卡藜灵\\n[医] 西印度苦香硷, 苦香硷","cascarilline":"[建] 卡藜灵","cascarin":"药鼠李苷, 波希鼠李素","casciano":"[人名] 卡夏诺","cascina":"[地名] [意大利] 卡希纳","casco":"蛋白质粘合剂","cascode":"射地-基地放大器, 共发共基放大器","cascoiodine":"[化] 酪碘; 碘化酪蛋白","cascophen":"酚醛树脂粘合剂","cascorez":"聚乙酸乙烯酯悬浮体粘合剂","casd":"[计]= Computer-Aided System Design,计算机辅助系统设计","case":"n. 情形, 情况, 箱, 容器, 事实, 病例, 案例, 框子\\nvt. 装箱, 包盖","case-book":"[法] 判例录编","case-by-case":"逐项给予","case-conference":"案例研讨会","case-conferences":"(case-conference 的复数) 案例研讨会","case-control":"病例对照","case-definition":"病例定义\\n诊断标准","case-definitions":"(case-definition 的复数) 病例定义\\n诊断标准","case-file":"专题案卷,案件卷宗","case-files":"(case-file 的复数) 专题案卷,案件卷宗","case-finding":"病例发现","case-harden":"[机] 铁材料之使表面硬化, 表面淬火","case-hardened":"a. 表面硬化的, 无情的","case-hardening":"[机] 表面硬化","case-histories":"(case-history 的复数) n. 病历；个案史","case-history":"n. 病历；个案史","case-law":"n. 判例法","case-laws":"(case-law 的复数) n. 判例法","case-lawyer":"[法] 精通案例的律师","case-load":"病例数","case-loads":"(case-load 的复数) 病例数","case-management":"病人管理","case-report":"病例报告","case-reporting":"[医] 病例报告","case-reports":"(case-report 的复数)  病例报告","case-sensitive":"a. 区分大小写的","case-studies":"(case-study 的复数) 实例分析\\n案例研究","case-study":"实例分析\\n案例研究","case-system":"[法] 以实际判例为基础的法律教学法","casealutine":"[化] l-异紫堇杷明","casease":"n. 酪蛋白酶\\n[医] 酪蛋白酶","caseate":"v. [病理]干酪化, 发生干酪样变","caseated":"vi. 干酪化, 发生干酪样变；干酪性坏死","caseates":"vi. 干酪化, 发生干酪样变；干酪性坏死","caseating":"n. 干酪样\\nv. 干酪样（caseate的ing形式）","caseation":"n. 干酪样变, 干酪化","casebearer":"n. [昆]鞘蛾幼虫","casebook":"n. 个案病例记录簿\\n[医] 病案簿","casebooks":"n. 个案记录簿；专题汇编集；病案簿","casebound":"a. (书籍)精装的","casec":"[医] 钙西克(酪蛋白钙的商品名)","casectomy":"[医] 干酪样灶溶解(结核病)","cased":"v. 包装；装入（case的过去式和过去分词形式）","caseful":"[网络] 个性化","casefy":"v. (使)变成干酪一般","caseharden":"vt. 使无情, 使表面硬化","casehardened":"a. 经热处理变硬的, 无感觉的, 麻木不仁的","casehardening":"v. 使无情, 使表面硬化( caseharden的现在分词 )","caseic":"[建] 酪朊的, 奶酪的","caseidin":"n. [生化]酪蛋白免疫素","caseification":"[医] 干酪化, 干酪性坏死","caseiform":"[医] 乳酪状的","casein":"n. 酪蛋白\\n[化] 酪蛋白","casein-formaldehyde":"[机] 酪蛋白-甲醛聚合物","casein-mercury":"[医] 酪蛋白汞","casein-sodium":"[医] 酪蛋白钠","caseinase":"[化] 酪蛋白酶","caseinate":"n. [化]金属(如钙或钠)与酪蛋白的化合物,酪蛋白酸","caseinates":"(caseinate 的第三人称 -s形式) n.[化]金属(如钙或钠)与酪蛋白的化合物,酪蛋白酸","caseinogen":"n. [生化]酪蛋白原","caseinogenate":"[医] 酪蛋白原酸盐","caseinum":"酪蛋白","casella":"[人名] 卡塞拉; [地名] [意大利] 卡塞拉","caselli":"[人名] 卡塞利","caseload":"[法] 工作量, 承办案件数","caseloads":"(caseload 的复数) [法] 工作量, 承办案件数","casemate":"n. 暗炮台, 炮塔","casemated":"a. 设有炮塔的, 有暗炮台的；设防坚固的","casemates":"(casemate 的第三人称 -s形式) n. 暗炮台, 炮塔","casement":"n. 窗, 玻璃窗","casemented":"a. casement的变形","casements":"n. 窗扉( casement的复数形式 )","caseogenous":"[医] 引起干酪化的","caseoiodine":"[医] 酪碘","caseoma":"干酪状结核瘤","caseophile":"n. 嗜干酪者","caseose":"n. [生化]酪朊","caseoserum":"[医] 抗酪蛋白血清","caseous":"a. 干酪的\\n[医] 干酪样的","caseouse":"[建] 酪状的","caser":"n. 大套管的专业队；装箱机","casern":"n. 要塞内的兵营","caserne":"n. 兵营[特指要塞地的]","Caserta":"n. (Caserta)人名；(法、意)卡塞尔塔","cases":"n. 案例；箱；情况（case的复数形式）","casesa":"[人名] 卡塞萨","casesiumphotocell":"[电] 铯光电池","casette":"n. 卡式","caseum":"[医]酪状碎屑","casework":"n. 社会工作","caseworker":"n. 社会工作者","caseworkers":"(caseworker 的复数) n. 社会工作者","caseworking":"(casework 的现在分词) n. 社会工作","caseworm":"n. 蓑虫\\n[医] 棘球绦虫","casey":"n. 凯西（男子名）","cash":"n. 现金\\nvt. 兑现","cash-and-carries":"n. <美>现购自运（的）( cash-and-carry的复数形式 )","cash-and-carry":"a. 付现自运的\\nn. 付现自运经营方式","cash-back":"现金返还","cash-book":"n. 现金账\\n[法] 现金簿, 现金出纳帐","cash-cow":"摇钱树；巨大财源","cash-cows":"(cash-cow 的复数) 摇钱树；巨大财源","cash-crop":"经济作物","cash-crops":"(cash-crop 的复数) 经济作物","cash-desk":"n. 收款台","cash-desks":"n. 收款处","cash-flow":"现金流转","cash-flows":"(cash-flow 的第三人称 -s形式) 现金流转","cash-in":"n. 债券等的兑现","cash-nexus":"银钱往来关系","cash-on-the-line":"[经] 货到立即付款, 签订销售合同立即付现","cash-out":"现金不足","cash-register":"现金出纳机, 收银机","cash-registers":"(cash-register 的复数) 现金出纳机, 收银机","cash-starved":"a. 周转资金不足的；资金短缺的","cash-strapped":"a. 缺乏现金的, 资金约束的; 经济困难的","cash-sweep":"[法] 现金结算","cashability":"[经] 变现能力","cashable":"a. 可兑现的","cashaw":"n. (cushaw之变体)红南瓜, 长颈南瓜","cashback":"现金提取（指借记卡持有者可在商店刷卡付账时提取小额现金, 此现金附加在购物账单上）","cashbook":"n. 现金帐簿","cashbox":"n. 钱箱","cashboxes":"(cashbox 的复数) n. 钱箱","cashboy":"n. 传递现款的小孩","cashcard":"n. 现金卡，提款卡","cashe":"藏镭器","cashed":"v. 把支票兑换成现金( cash的过去式 )","Cashel":"n. (Cashel)人名；(英)卡谢尔","cashen":"[人名] [爱尔兰姓氏] 卡申 McCashin的变体","casher":"n. 出纳员","cashes":"v. 把支票兑换成现金( cash的第三人称单数 )","cashew":"n. 腰果树, 腰果\\n[化] ┐如树; 腰果树","cashew-nut":"[医] ┊如实, ┊如坚果","cashews":"n. 腰果, 腰果树( cashew的复数形式 )","cashflow":"vi. 现金流转","cashflows":"(cashflow 的复数) vi. 现金流转","cashier":"n. 出纳员\\n[经] 司库, 出纳员, 收支员","cashiered":"v. 革除（军官）职务( cashier的过去式 )","cashierer":"n. (商店等的)出纳员；出纳主任；(银行或公司的)司库","cashiering":"v. 革除（军官）职务( cashier的现在分词 )","cashiers":"n. 出纳员( cashier的名词复数 )","cashin":"[人名] [爱尔兰姓氏] 卡欣 McCashin的变体","cashing":"[经] 把...兑现","cashion":"[人名] [爱尔兰姓氏] 卡申 McCashin的变体","cashless":"a. 无现款的,无现金的,无钱的","cashman":"[人名] [英格兰人姓氏] 卡什曼 Case的变体; [人名] [爱尔兰姓氏] 卡什曼盖尔语姓氏的英语形式，来源于人名，含义是“预言者”(oracle)","cashmere":"n. 开士米, 山羊绒\\n[化] 山羊绒; 开斯米绒","cashmeres":"(cashmere 的复数) n. 开士米, 山羊绒\\n[化] 山羊绒; 开斯米绒","cashmerette":"n. [纺]仿开士米斜纹绒,仿开士米织物","cashmore":"[人名] [英格兰人姓氏] 卡什莫尔住所名称，来源于古英语，含义是“水芹+沼泽”(cress+fen,marsh)","cashomat":"[计] 自动提款机","cashoo":"n. [化]儿茶","cashpoint":"[经] 一种电脑化的付现机","cashpoints":"n. 自动提款机( cashpoint的复数形式 )","cashton":"[地名] [美国] 卡什顿","casi":"abbr. 知能筛检工具（Cognitive Abilities Screening Instrument）；加拿大宇宙航行研究所（Canadian Aeronautics and Space Institute）","CASIA":"化学文摘题目索引通报","casial":"(文法上)格的,关于格的","casilda":"[地名] [阿根廷、古巴] 卡西尔达","casillas":"[人名] 卡西拉斯; [地名] [危地马拉] 卡西亚斯","casimir":"仿开士米薄呢","casimire":"n. 薄毛呢","Casimiroa":"[医] 掌叶瓜橘属(芸香科)","casimiroedine":"[化] 卡西定","casimiroin":"[化] 卡西碱","casimiroine":"咖锡碱","casing":"n. 箱, 盒, 包装, 框, 套管\\n[化] 汽车外胎","casinghead":"套管头","casings":"n. 框( casing的名词复数 ); 壳; 罩; 套","casino":"n. 卡西诺赌场, 卡西诺牌戏","casino-hotel":"[网络] 赌场旅馆；赌场酒店；赌场饭店","casinos":"n. （意）乡间住宅；赌场；娱乐场（casino的复数）","casio":"n. 卡西欧（日本电子品牌）","casita":"n. 小屋","casiumbiotite":"铯黑云母","cask":"n. 桶, 木桶\\nvt. 装入桶内","caska":"卡仕达","casket":"n. 首饰盒, 小箱, 匣子, 棺材","caskets":"n. 首饰盒, 匣子, <美>棺材( casket的复数形式 )","caskey":"[人名] 卡斯基","caskful":"[网络] 桶装","casks":"n. （尤指盛酒精饮料的）桶( cask的复数形式 ); 一桶的量","Caslen":"[美]卡斯纶(酪蛋白单丝)","casley":"[人名] 凯斯利","Caslon":"n. 卡斯龙(英国人,1692-1766)铝制活字","caslox":"合成树脂结合剂","Casmerodius":"[网络] 大白鹭属","casner":"[人名] 卡斯纳","caso":"abbr. Canada Southern Railroad 加拿大南方铁路公司; Civil Aviation Safety Order 民用航空安全命令","Casolana":"[荷兰]卡索拉纳(酪蛋白短纤维)","Casolate":"氯灭杀威(农药)","cason":"[人名] 卡森; [地名] [美国] 卡森; [地名] [意大利] 卡索利","casoria":"[地名] [意大利] 卡索里亚","casos":"abbr. Center for Advanced Study in Organization Science (U of Wisconsin) 组织科学高级研究中心（威斯康辛大学）","casp":"abbr. caspase 半胱天冬酶; Capability Support Plan 能力支持计划; Cape Arago State Park (Oregon) 坎普阿拉果国家公园（俄勒冈州）; Commodity Assistance Program <澳大利亚>商品援助计划","Caspar":"n. 卡斯帕（《圣经》中三哲士之一, 等于Gaspar）","caspase":"[医]半胱天冬酶","caspases":"[医]胱门蛋白酶","casper":"一个卡通造型, 为一可爱的小精灵","caspers":"abbr. Computer-Automated Speech-Perception-System 计算机自动化言语感受系统","caspersen":"[人名] 卡斯佩森","caspi":"[人名] 卡斯皮","Caspian":"a. 里海的","caspofungin":"[医]卡泊芬净<抗真菌药>","casque":"n. 盔","casques":"(casque 的复数) n. 盔","casquet":"n. 无面甲轻型头盔","casquetel":"轻型敞开头盔","casquette":"n. (有遮阳的)盔式无边帽","cass":"abbr. 货物财务结算系统（Cargo Account Settlement System）；指令主动声纳浮标系统（Commanded Active Sonobuoy System）","cassa":"abbr. Continental Army Command Automated System Support Agency <美国>大陆军队指挥部自动系统支援局","cassab":"n. 亚洲籍商船水手","cassaba":"n. (=casaba)[植]卡萨巴甜瓜(原产于土耳其卡萨巴地方)","cassabanana":"香蕉瓜","cassada":"n. 树薯;树薯根制的淀粉","Cassadagan":"凯瑟达格统","cassady":"[人名] 卡萨迪","cassaidine":"[化] 二氢围涎皮次碱\\n[医] 二氢围涎皮次硷","cassaine":"[化] 围涎皮次碱\\n[医] 围涎皮次硷","cassamine":"围涎皮胺","Cassandra":"n. 卡珊德拉, 凶事预言家, 不为人所信的预言家","cassandras":"n. 不为人所信的吉凶预言者（Cassandra的复数）","cassard":"[人名] 卡萨德","cassareep":"n. 木薯浓汁","cassas":"卡瑟斯松捻细平布","cassata":"n. 卡萨塔冰淇淋","cassate":"cassate (third-person singular simple present cassates, present participle cassating, simple past and past participle cassated)\\n(obsolete) To render void or useless; to vacate or annul.\\n","cassation":"n. 撤消原判\\n[法] 废弃, 废除, 翻案","cassations":"(cassation 的复数) n. 撤消原判\\n[法] 废弃, 废除, 翻案","Cassatt":"卡萨特（人名）","cassava":"n. 木薯\\n[医] 木薯","cassave":"木薯,树薯(粉),珍珠粉","cassawa":"[建] 木薯","casse":"<法>n.(某些酒的)变质","Cassegrain":"n. 卡塞格伦望远镜(亦作Cassegrain telescope)","Cassegrainian":"n. 卡塞格伦望远镜(亦作Cassegrain telescope)","Cassel":"卡塞尔[德意志联邦共和国东部城市]","Cassell":"n. (Cassell)人名；(法)卡塞尔；(英)卡斯尔；(西)卡塞利","Cassells":"(Cassell 的第三人称 -s形式) n. (Cassell)人名；(法)卡塞尔；(英)卡斯尔；(西)卡塞利","casselman":"[人名] 卡斯尔曼; [地名] [加拿大] 卡斯尔曼","Cassels":"(Cassel 的复数) 卡塞尔[德意志联邦共和国东部城市]","casserly":"[人名] [英格兰人姓氏] 卡瑟利 Cassidy的变体","casserole":"n. 餐桌上用有盖的焙盘, 砂锅菜\\n[化] 勺皿","casseroled":"n. 勺皿；砂锅菜；餐桌上用有盖的焙盘\\nvi. 用焙盘焙","casseroles":"n. 焙盘( casserole的复数形式 ); 砂锅; 焙盘菜; 砂锅菜","casseroling":"n. 勺皿；砂锅菜；餐桌上用有盖的焙盘\\nvi. 用焙盘焙","cassette":"n. 盒式磁带, 珠宝箱, 暗盒\\n[计] 字盒","cassette-recorder":"[电讯] 盒式录音机","cassette-recorders":"(cassette-recorder 的复数) [电讯] 盒式录音机","cassettes":"n. 盒式录音带( cassette的复数形式 ); 盒式磁带; 卡式磁带; （胶片）暗盒","cassi":"abbr. Cassiopeia 仙后座","cassia":"n. 肉桂\\n[医] 桂皮, 肉桂, 中国桂皮","cassia-wood":"[医] 决明木","cassiachromone":"决明色酮, 羟基甲基氧丙基苯并吡喃酮","cassiday":"[人名] 卡西迪","cassideous":"盔状的","Cassidulinacea":"盔有孔虫总科","Cassiduloida":"盔海胆目","Cassidy":"n. 卡西迪（男子名）","Cassidys":"(Cassidy 的复数) n. 卡西迪（男子名）","Cassie":"n. 卡西(Cass的异体)(f.)","cassilly":"[人名] 卡西利","cassilysidin":"[医] 决明皮素","cassilysin":"决明皮溶素","cassimere":"n. 薄毛呢","cassimerette":"低级薄毛呢","Cassin":"卡森(Rene, 1887-1976, 法国政治家, 曾获1968年诺贝尔和平奖)","cassina":"冬青茶(茶叶代用品)","cassine":"山扁豆碱","cassinelli":"[人名] 卡西内利","cassinet":"卡西奈特厚斜纹织物, 卡西奈特阿尔帕卡花呢","cassinette":"卡西奈特呢","cassingham":"[人名] 卡辛厄姆","cassini":"n. 卡西尼号（太空船）\\nn. (Cassini)人名；(俄、法、西、意、葡、英)卡西尼","cassini-huygens":"卡西尼－惠更斯号","cassinite":"钡正长石","Cassino":"n. 一种纸牌戏(由二至四人玩)","cassinoid":"卡西尼卵形线","cassiodorus":"卡西奥多罗斯","Cassiope":"[网络] 锦绦花属；岩须属；卡西俄佩","Cassiopeia":"n. 仙后座","Cassiopeids":"[天]仙后(座)流星群","cassiopeium":"[化]镥(71号元素, 符号Lu)","Cassirer":"n. 卡希雷尔（德国犹太哲学家）","cassiri":"木薯酒","cassis":"n. 产于欧洲的黑醋栗, 黑醋栗所酿的酒","Cassite":"[网络] 加瑟人","cassiterite":"n. 锡石\\n[化] 锡石","cassiterolamprite":"黄锡矿","cassiterotantalite":"锰钽矿","cassity":"[人名] 卡西蒂","cassius":"n. 卡西乌斯（罗马共和国末期的将领）","casso":"abbr. Command Active Sonobuoy System 指令主动声呐浮标系统（机载反潜侦察器）; Connecticut Association of Secondary Schools 康涅狄格中等教育协会","cassock":"n. 法衣, 袈裟","cassocked":"a. 身着法衣的","cassocks":"n. （教士穿的黑色或红色的）长袍( cassock的复数形式 ); 法衣","cassolette":"熏香盒香炉","Casson":"n. (Casson)人名；(法、西)卡松；(英)卡森","cassonade":"[建] 粗糖","cassopolis":"[地名] [美国] 卡索波利斯","cassoulet":"n. 豆焖肉","cassoulets":"(cassoulet 的复数) n. 豆焖肉","cassowaries":"n. 食火鸡( cassowary的名词复数 )","cassowary":"n. 食火鸡","cassowarys":"(cassowary 的复数) n. 食火鸡","cassrole":"小勺皿","cassumunar":"[医] 印度姜","cassville":"[地名] [美国] 卡斯维尔","cassyfiline":"卡西飞林; 无根藤碱","cassythidine":"无根藤次碱","cast":"n. 演员阵容, 投掷, 铸件, 预测, 特性\\nvt. 投, 掷, 抛, 脱落, 铸, 使弯曲, 计算\\nvi. 投, 计算, 浇铸成型","cast-in-place":"就地浇铸","cast-iron":"a. 铸铁的, 铸铁制成的, 坚固的, 不妥协的\\n[电] 铸铁","cast-off":"遭遗弃的; 版面计算","cast-offs":"(cast-off 的复数)  遭遗弃的; 版面计算","cast-on":"熔补; 点冒口","cast-steel":"[电] 铸钢","castability":"[机] 可铸性, 铸造性","castable":"铸块的, 可浇铸材料的; 注块","Castagnea":"凯氏褐藻属","castaic":"[地名] [美国] 卡斯泰克","Castalia":"n. (=Castaly)神泉, 诗之泉","Castalian":"a. 诗之泉的, 灵感源泉的","Castalians":"(Castalian 的复数) adj.诗之泉的, 灵感源泉的","Castalie":"n. (=Castaly)神泉, 诗之泉","castalogne":"卡斯塔隆毛毯呢","Castaly":"n. 卡斯塔利亚泉, 诗之泉, 灵感的源泉","castamargina":"[医] 卡斯塔马吉纳(墨西哥植物Castela tortuosa的一种甙,可治阿米巴痢疾)","castana":"巴西干果树","castanea":"[化] 齿栗叶","castaneous":"a. 栗色的","castanet":"n. 响板(用硬木或象牙制成的)","castanets":"n. 响板","castanetting":"(castanet 的现在分词) n. 响板(用硬木或象牙制成的)","castanite":"褐铁矾","Castanopsis":"栲属","Castanospermum":"[网络] 栗豆树属","castaway":"n. 被抛弃的人, 坐船遇难者\\na. 被抛弃的, 遭难的","castaways":"n. 被抛弃的人, 坐船遇难者, 漂流者( castaway的复数形式 )","caste":"n. 印度的种姓制度, (排他的)社会团体","casteel":"[人名] 卡斯蒂尔","casteen":"[人名] 卡斯廷","casteism":"n. （印度的）种性制度","castel":"n. 卡斯特尔（法国公司名）","Castela":"[建] 堡树属","castelamarin":"[化] 堡树苦素","casteless":"a. 没有社会阶级的, （在印度）不属于任何阶级的","castelet":"小城堡","Castell":"卡斯泰尔(德国地名)","castella":"n. (Castella)人名；(西)卡斯特利亚；(意、法)卡斯泰拉","castellamonte":"[地名] [意大利] 卡斯特拉蒙特","castellan":"n. 城堡总管, 要塞司令","castellane":"[地名] [法国] 卡斯特拉讷","Castellanella":"[医] 卡[斯太拉尼]氏锥虫属","castellaneta":"[地名] [意大利] 卡斯特拉内塔","Castellania":"[医] 卡[斯太拉尼]氏真菌属","castellanies":"n. 城主之阶级","castellano":"n. (Castellano)人名；(英、西)卡斯特利亚诺；(意)卡斯泰拉诺","castellanos":"[地名] [西班牙] 卡斯特利亚诺斯山","castellans":"(castellan 的复数) n. 城堡总管, 要塞司令","castellanus":"堡状(云)的","castellany":"n. 城主之阶级(职位, 辖区)","castellar":"a. 城堡的, 似城堡的","castellate":"n. 城主之阶级、职位或辖区","castellated":"a. 造成城形的, 构造如城的, 有城的","castellation":"n. 城堡状建筑, 雉堞墙","castellations":"(castellation 的复数) n. 城堡状建筑, 雉堞墙","Castelli":"n. (Castelli)人名；(英、意)卡斯泰利","Castello":"n. (Castello)人名；(西)卡斯特略；(法、芬、意)卡斯泰洛","Castelnau":"n. (Castelnau)人名；(法)卡斯泰尔诺","castelo":"n. (Castelo)人名；(西、葡)卡斯特洛","caster":"n. 投手, (家具的)脚轮, 调味瓶\\n[机] 后倾角","casters":"(caster 的复数) n. 投手, (家具的)脚轮, 调味瓶\\n[机] 后倾角","casterton":"[地名] [澳大利亚、英国] 卡斯特顿","castes":"n. 印度的社会等级( caste的复数形式 ); 任何排他的社会阶层; 种姓（按照血统、阶级、财富等严格区分的社会制度）","castetter":"[人名] 卡斯泰特","castex":"[医] 盒装石膏绷带(特制成品)","castice":"n. 在东印度群岛出生和居住的葡萄牙人","casticin":"紫花牡荆素","castigate":"vt. 惩罚, 苛评, 修订","castigated":"v. 严厉责骂、批评或惩罚（某人）( castigate的过去式 )","castigates":"v. 严厉责骂、批评或惩罚（某人）( castigate的第三人称单数 )","castigating":"v. 严厉责骂、批评或惩罚（某人）( castigate的现在分词 )","castigation":"n. 惩罚, 苛评, 修订","castigations":"(castigation 的复数) n. 惩罚, 苛评, 修订","castigator":"n. 鞭打者, 修订者, 申斥者","castigatory":"a. 申斥的, 惩罚的, 修订的","Castiglione":"卡斯蒂廖内（人名）","Castile":"[常castile ]用橄榄油和碱制成的, 卡斯提尔(古代西班牙北部一王国)","Castilian":"a. 卡斯蒂利亚的\\nn. 卡斯蒂利亚人, 卡斯蒂利亚语","Castilians":"(Castilian 的复数) a. 卡斯蒂利亚的\\nn. 卡斯蒂利亚人, 卡斯蒂利亚语","Castilla":"卡斯蒂利亚[西班牙中部和北部一地区]","castille":"[人名] 卡斯蒂尔","Castilleia":"[网络] 卡斯蒂利亚","Castilleja":"[网络] 火焰草属；扁萼花属；火焰草属植物","castillejo":"[地名] [委内瑞拉] 卡斯蒂耶霍","Castillian":"[网络] 卡斯提尔语；卡斯提尔文；卡斯蒂利雅人","castillite":"杂斑铜矿","Castillo":"n. 卡斯蒂略（人名）","castilloa":"美胶树","castillos":"[地名] [乌拉圭] 卡斯蒂约斯","castine":"[化] 牡荆碱","casting":"n. 投掷, 铸成品, 角色分配\\n[化] 浇铸; 铸品","castings":"n. 铸造（物）( casting的复数形式 ); 角色的分派; 投; 放弃","castiron":"a. 铸铁制成的,不屈的,严厉的","castle":"n. 城堡, 象棋中的车\\nvt. 置于城堡中, 盘踞于","castle-builder":"n. 空想家","castle-guard":"n. 佃农在战时防卫城堡之义务","castleberry":"[人名] 卡斯尔伯里; [地名] [美国] 卡斯尔伯里","castled":"a. 有城堡的, 如城堡的","castlemaine":"[地名] [爱尔兰、澳大利亚] 卡斯尔梅恩","castleman":"[人名] [英格兰人姓氏] 卡斯尔曼 Castle的变体","Castlereagh":"n. (Castlereagh)人名；(英)卡斯尔雷","castlerock":"[地名] [英国] 卡斯尔罗克","castles":"n. 城堡, 堡垒( castle的名词复数 )","Castleton":"n. (Castleton)人名；(英)卡斯尔顿","castlevania":"恶魔城系列","castlewood":"[地名] [美国] 卡斯尔伍德","castling":"n. 王车易位","castnet":"n. (撒出后又立即收回的)撒网","Castniidae":"蝶蛾科","Castnioidea":"蝶蛾总科","casto":"[人名] 卡斯托","castock":"n. <苏>白菜梗","castoff":"n. 被丢弃的人\\n[计] 封锁消息","castoffs":"(castoff 的复数) n. 被丢弃的人\\n[计] 封锁消息","castolin":"铸铁焊料合金","CASTON":"[计] 开放消息","castonguay":"[人名] 卡斯顿圭","castor":"n. 调味瓶, 海狸\\n[机] 脚轮","castor(eum)":"[化] 海狸香","castor-oil":"[医] 蓖麻油","castoral":"卡斯特罗(蓖麻油与矿物油的混合物)","castoramine":"海狸胺","Castordag":"(胶体石墨和蓖麻油组成的)液体润滑剂","castorette":"充河狸皮","castoreum":"n. 海狸香( 海狸性腺产生的一种浓味香料)","castoria":"卡斯托里阿(成药, 小儿轻泻剂)","Castoridae":"[动]河狸科","castorin":"海狸香素","castorite":"透锂长石","Castoroides":"大河狸属","castors":"n. （家具的）小脚轮( castor的复数形式 ); 调味品瓶","castory":"海狸香","castrametation":"n. 设置军营, 营址设置术","castrate":"vt. 阉割, 删除, 使丧失力量(或效果)\\n[医] 去生殖腺者, 阉者, 阉, 阉割","castrated":"a. [医]去势的, 阉割的, 去雄的\\nv. 阉割（动物、人）( castrate的过去式 )","castrates":"v. 阉割（动物、人）( castrate的第三人称单数 )","castrati":"n. 阉人歌手（castrato的复数）\\nn. (Castrati)人名；(意)卡斯特拉蒂","castrating":"v. 阉割（动物、人）( castrate的现在分词 )","castration":"n. 去雄蕊, 修正, 阉割\\n[医] 阉, 阉割(睾丸或卵巢切除术)","castrations":"(castration 的复数) n. 去雄蕊, 修正, 阉割\\n[医] 阉, 阉割(睾丸或卵巢切除术)","castrative":"a. 产生阉割效果的","castrato":"n. 被阉的男歌手","castrator":"[医]家畜去势器（兽医用）","castratory":"a. castrate的变形","castratos":"(castrato 的复数) n. 被阉的男歌手","Castres":"n. (Castres)人名；(法)卡斯特","Castries":"卡斯特里[拉丁美洲岛国圣卢西亚首都](或译卡斯特里斯)","Castrix":"鼠立死(农药)","Castro":"n. 卡斯特罗（古巴领导人, 1976-2006年在任）","castroid":"[医] 类阉者, 类无睾者","Castroism":"n. 卡斯特罗主义(即古巴共产党领导人卡斯特罗的政治主张)","Castroite":"n. 卡斯特罗主义者, 卡斯特罗之追随者\\na. 卡斯特罗的","Castroites":"(Castroite 的复数) n.卡斯特罗主义者, 卡斯特罗之追随者\\na. 卡斯特罗的","castrol":"[建] 凯斯特罗","castrophrenia":"[医] 思想被摄妄想","castroville":"[地名] [美国] 卡斯特罗维尔","casts":"n. 演员阵容；管型（cast的复数）","castte":"n. 城堡","casual":"a. 偶然的, 不经意的, 便装的\\nn. 临时工, 待命士兵","casualies":"受伤者,意外,灾难 (复数)","casualism":"n. 偶然说, 机缘说","casualist":"n. 机缘说, 偶然说；偶然状态 (casualism的变形)","casualities":"(casuality 的复数) n. 因果律","casuality":"n. 因果律","casualization":"n. 转为雇用临时工制, 雇用临时工制","casualize":"vt.将(正式工)转为临时工","casually":"adv. 偶然地, 临时地, 随便地","casualness":"n. 偶然","casuals":"n. [复数]便鞋( casual的复数形式 ); [军事]待命士兵; 没有固定工作的劳动者; [英国英语][亦作C-]（穿着休闲服、政治上较偏激的）休闲暴力者","casualties":"n. 伤亡；人员伤亡（casualty的复数）","casualty":"n. 意外事故, 伤亡, 受害者\\n[化] 事故","casualy":"adv. 不拘礼节地；漫不经心地；随意地","Casuaridae":"[网络] 木麻黄科","Casuariidae":"鹤鸵科","Casuariiformes":"鹤鸵目","casuarina":"n. 木麻黄","Casuarinaceae":"木麻黄科","Casuarinales":"木麻黄目","casuarinas":"(casuarina 的复数) n. 木麻黄","Casuarius":"[网络] 鹤鸵属；犀鸟亚科；食火鸡","casuist":"n. 决疑论者, 诡辩家","casuistic":"a. 决疑的, 诡辩的","casuistical":"a. 决疑的, 诡辩的","casuistics":"n. 决疑论, 良心论","casuistry":"n. 决疑论, 决疑法, 诡辩","casuists":"(casuist 的复数) n. 决疑论者, 诡辩家","casuitically":"adv. 决疑地, 诡辩地","casurin":"木麻黄素","casus":"n. 案例\\n[法] 案例, 原因, 事故","casusbelli":"开战的理由, 宣战的借口","casusfoederis":"条约中所涉及的事项","Caswell":"n. (Caswell)人名；(英)卡斯韦尔","cat":"n. 猫, 恶妇\\nvi. 呕吐\\n计算机辅助教育, 计算机辅助测试, 计算机辅助翻译, 计算机辅助排版\\n[计] 计算机辅助教学, 计算机辅助翻译, 计算机辅助排字, 计算机辅助测试","cat's-claw":"n. 【植物】猫爪猴耳环(Pithecellobium unguis-cati)[亦作 catclaw,亦称作 blackbead]","cat's-ear":"n. 猫耳草","cat's-eye":"n. 猫儿眼, 猫睛石","cat's-foot":"n. 欧亚活血丹, 蝶须","cat's-meat":"n. 喂猫用的肉","cat's-paw":"n. 受人利用者","cat's-tail":"n. 【植】问荆\\n[网络] 猫尾巴西点蛋糕坊","cat's-whisker":"n. 触须, 晶须","cat-":"pref. 在下, 关于, 完全, 相反, 反对","cat-and-dog":"a. 吵吵闹闹的, 不和的","cat-and-mouse":"adj. 折磨人的，一捕一放之捉弄人的","cat-blend":"n. 催化裂化残油与直馏残油混合物\\n[建] 催化裂化残油与直馏残油混合物","cat-call":"n. 嘘声；不满之声；喝倒采\\nvi. 发嘘声；发尖叫声\\nvt. 发嘘声","cat-calls":"(cat-call 的复数) n. 嘘声；不满之声；喝倒采\\nvi. 发嘘声；发尖叫声\\nvt. 发嘘声","cat-cracker":"[化] 催化裂解装置","cat-eyed":"a. 能在黑暗中视物的","cat-foot":"vi. 象猫似地偷偷摸摸前进","cat-footed":"a. 猫足似的, 静悄悄的(走路)","cat-like":"像猫一样的","cat-o'-nine-tails":"n. 九尾鞭","cat-rigged":"a. 装有单帆艇式之索具的","cat-scan":"abbr. computerized axial tomography scan that depicts body structures not shown by conventional X-ray procedures 计算机化X射线轴向分层造影，使用这种方法可","cata":"[机] 渺位","cata-":"[前缀]表示“下, 向下”之义","cata-cornered":"[网络] cata角","catabaptist":"n. 反对婴儿行洗礼者, 再洗礼教徒","catabases":"连事撤退,下降 (复数)","catabasial":"颅底点低的","catabasis":"[医] 缓解期","catabatic":"a. 下降的, 减少的, 缓解的","catabions":"分解优势生物","catabiosis":"分解代谢, 异化(作用)","catabiotic":"[医] 异化消耗的","catabolergy":"[医] 异化能量消耗","catabolic":"a. 分解代谢的\\n[医] 分解代谢的, 异化的","catabolically":"adv. 分解代谢","catabolin":"分解代谢产物; 异化产物","catabolise":"vt., vi. [主英国英语]＝ catabolize","catabolism":"n. 异化作用, 分解代谢\\n[化] 分解代谢; 降解代谢","catabolite":"n. 新陈代谢作用之副产物","catabolize":"v. (使)异化, (使)发生分解代谢","catabolized":"v. （使）异化, （使）发生分解代谢( catabolize的过去式和过去分词 )","catabolizes":"v. （使）异化, （使）发生分解代谢( catabolize的第三人称单数 )","catabolizing":"v. （使）异化, （使）发生分解代谢( catabolize的现在分词 )","catabythismomania":"[医] 投水狂, 自溺狂","catabythismus":"[医] 投水自杀","Catacala":"[网络] 卡塔卡拉","catacausis":"[医] 自燃","catacaustic":"a. [物]回光线的\\nn. 回光线(diocaustic之对)","catachosis":"[地质]碎裂变质","catachresis":"n. 在特定上下文中词的误用, 修辞手法生硬而自相矛盾的误用","catachrestic":"a. 用词不当的, 修辞生硬且自相矛盾的误用","catachrestical":"a. catachresis的变形","catachrestically":"adv. 用词不当地, 修辞生硬且自相矛盾的误用地","catachromasis":"末期核变, 子(细胞)核建成","cataclase":"破碎, 岩石破碎","cataclasis":"n. [地]岩石碎裂,碎裂作用","cataclasite":"n. 碎裂岩","cataclasm":"n. 碎裂","cataclastic":"a. 碎裂的","catacleisis":"眼睑封闭","cataclinal":"a. 与地层凹陷处同方向下降的, 顺斜的","catacline":"下倾型","cataclonus":"[医] 齐整阵挛","cataclysm":"n. 大洪水, 地震, (社会政治的)大变动\\n[医] 渗出, 渗液, 猝变, 聚变","cataclysmal":"a. 洪水的, 灾变的, 政治和社会大变动的","cataclysmic":"a. 洪水的, 灾变的, 政治和社会大变动的","cataclysmically":"adv. cataclysmic的变形","cataclysms":"n. （突然降临的）大灾难( cataclysm的复数形式 )","catacomb":"n. 地下墓穴, 地窖","catacombs":"n. 地下墓穴, 陵寝","catacorner":"[网络] 碰撞者","catacorolla":"副花冠","catacoustics":"n. 回音学","catacrotic":"[医] 降线一波[脉]的","catacrotism":"降线-波脉(现象)","catactrophic":"[计] 灾难性的","catadicrotic":"[医] 降线二波[脉]的","catadicrotism":"[医] 降线一波脉[现象]","catadidymus":"[医] 下身联胎, 双上身联胎","catadioptric":"a. 兼反射光及折射光的","catadioptrics":"n. 兼反射光及折射光; 反折射学","catadrome":"[医] 减退","catadromically":"向上地","catadromous":"a. 下海产卵的","catafactor":"冷却温度计因子","catafalque":"n. 灵柩台, 灵柩车","catafalques":"(catafalque 的复数) n. 灵柩台, 灵柩车","catafighter":"弹射起飞的战斗机","catafront":"下滑锋","catagelophobia":"[医] 嘲笑恐怖[病]","catagen":"毛发生长中期","catagenesis":"n. 退化, 复旧\\n[医] 退化","catageolophobia":"[心理]嘲笑恐怖","catagma":"骨折","catagmatic":"[医] 促使骨折愈合的","catahymenium":"(pl. -nia) 不齐子实层","catal":"abbr. catalog 目录; 目录册; 编目录; catalogue 目录","Catalan":"n. 加泰隆人, 加泰隆语","catalanguage":"[计] 目标语言, 结果语言","Catalanist":"n. 加泰罗尼亚独立主义分子","Catalanists":"(Catalanist 的复数) n.加泰罗尼亚独立主义分子","Catalans":"(Catalan 的复数) n. 加泰隆人, 加泰隆语","catalase":"n. 过氧化氢酶\\n[化] 过氧化氢酶; 催化酶; 触酶","catalase-azide":"[医] 过氧化氢酶迭氮物","catalasometer":"[化] 催化酶活度计","catalatic":"[医]过氧化氢酶的, 触酶的","catalator":"酶模型, 过氧化氢酶模型","catalectic":"a. 音步不完全的, 最后音步缺少音节的\\nn. 最后的音步中缺少音节的诗行","catalepsis":"n. 强直性昏厥, 僵住状, 倔强症","catalepsy":"n. 强直性昏厥, 僵住状, 倔强症\\n[医] 僵住症, 强直性昏厥, 倔强症","catalept":"(孢粉)近极薄壁区"}